{"<end>": 0, ".": 1, "the": 2, "to": 3, "a": 4, ",": 5, "is": 6, "!": 7, "?": 8, "of": 9, "in": 10, "and": 11, "\\": 12, "this": 13, "$url$": 14, "that": 15, "for": 16, "you": 17, "i": 18, "it": 19, "not": 20, "@bbcbreaking": 21, "@whitehouse": 22, "...": 23, "be": 24, "are": 25, "on": 26, "he": 27, "they": 28, ":": 29, "have": 30, "@foxnews": 31, "what": 32, "with": 33, "so": 34, "@cnnbrk": 35, "@cnn": 36, "\"": 37, "was": 38, "all": 39, "but": 40, "just": 41, "ud83d": 42, "no": 43, "will": 44, "if": 45, "url": 46, "@potus": 47, "@bbcnews": 48, "like": 49, "about": 50, "we": 51, "people": 52, "@espn": 53, "@realdonaldtrump": 54, "at": 55, "how": 56, "ude": 57, "do": 58, "your": 59, "@hillaryclinton": 60, "has": 61, "as": 62, "up": 63, "@berniesanders": 64, "don't": 65, "why": 66, "his": 67, "it's": 68, "who": 69, "from": 70, "more": 71, "&": 72, "or": 73, "get": 74, "can": 75, "out": 76, "@abc": 77, "them": 78, "her": 79, "trump": 80, "one": 81, "-": 82, "an": 83, "now": 84, "would": 85, "she": 86, "by": 87, "there": 88, "should": 89, "when": 90, "my": 91, "good": 92, "that's": 93, "obama": 94, "me": 95, "him": 96, "/": 97, "\u201c": 98, "their": 99, "@huffingtonpost": 100, "\u201d": 101, "did": 102, "n": 103, "go": 104, "..": 105, "us": 106, "know": 107, "our": 108, "'": 109, "think": 110, "white": 111, "only": 112, "time": 113, "too": 114, "i'm": 115, "right": 116, "hillary": 117, "@drudge_report": 118, "been": 119, "@cnnpolitics": 120, "president": 121, "@msnbc": 122, "well": 123, "see": 124, "news": 125, "@nytimes": 126, "really": 127, "some": 128, "these": 129, "over": 130, "after": 131, "house": 132, "@shaunking": 133, "@politico": 134, "than": 135, "make": 136, "then": 137, "much": 138, "can't": 139, "going": 140, "still": 141, "want": 142, "were": 143, "u": 144, "does": 145, "say": 146, "never": 147, "take": 148, "@gotham3": 149, "need": 150, "those": 151, "man": 152, "any": 153, "great": 154, "even": 155, ")": 156, "way": 157, "had": 158, "(": 159, "because": 160, "2": 161, "he's": 162, "lol": 163, "world": 164, "god": 165, "back": 166, "its": 167, "being": 168, "where": 169, "doesn't": 170, "$": 171, "police": 172, "stop": 173, "love": 174, "s": 175, "same": 176, "country": 177, "america": 178, "day": 179, "@newswatch33": 180, "down": 181, "many": 182, "new": 183, "oh": 184, "sad": 185, "udc": 186, "women": 187, "very": 188, "said": 189, "@nbcnightlynews": 190, "other": 191, "@cnni": 192, "real": 193, "didn't": 194, "1": 195, "could": 196, "better": 197, "off": 198, "wow": 199, "target": 200, "here": 201, "@target": 202, "years": 203, "wrong": 204, "nothing": 205, "@buzzfeed": 206, "@theonion": 207, "isn't": 208, "look": 209, "again": 210, "true": 211, "sure": 212, "please": 213, "@bbcworld": 214, "02": 215, "@thevalleyreport": 216, "ever": 217, "most": 218, "got": 219, "rt": 220, "first": 221, "let": 222, "says": 223, "hope": 224, "money": 225, "clinton": 226, "@lhfang": 227, "rainbow": 228, "%": 229, "another": 230, "media": 231, "before": 232, "@reuters": 233, "thing": 234, "also": 235, "believe": 236, "into": 237, "come": 238, "thank": 239, "men": 240, "black": 241, "pay": 242, "@ap": 243, "maybe": 244, "bad": 245, "gay": 246, "vote": 247, "something": 248, "4": 249, "yes": 250, "@eonline": 251, "keep": 252, "against": 253, "anything": 254, "must": 255, "shit": 256, "work": 257, "you're": 258, "@thehill": 259, "bernie": 260, "use": 261, "ud83c": 262, "probably": 263, "@mashable": 264, "made": 265, "watch": 266, "job": 267, "done": 268, "@usatoday": 269, "looks": 270, "woman": 271, ":/": 272, "dead": 273, "american": 274, "put": 275, "support": 276, "stupid": 277, "w": 278, "give": 279, "@rockprincess818": 280, "they're": 281, "@rollingstone": 282, "someone": 283, "@franklin_graham": 284, "big": 285, "r": 286, "may": 287, "live": 288, "@lrihendry": 289, "own": 290, "anyone": 291, "thought": 292, "americans": 293, "hostages": 294, "won't": 295, "killed": 296, "gun": 297, "@newsweek": 298, "doing": 299, "always": 300, "tell": 301, "everyone": 302, "show": 303, "read": 304, "guess": 305, "@caitlyn_jenner": 306, "next": 307, "such": 308, "what's": 309, "guy": 310, "which": 311, "every": 312, "enough": 313, "actually": 314, "lies": 315, "state": 316, "yeah": 317, "thanks": 318, "law": 319, "marriage": 320, "\u2019": 321, "yet": 322, "hell": 323, "needs": 324, "help": 325, "best": 326, "@loudobbs": 327, "makes": 328, "guns": 329, "win": 330, "am": 331, "lie": 332, "muslim": 333, "under": 334, "*": 335, "while": 336, "mean": 337, "already": 338, "isis": 339, "usa": 340, "@breitbartnews": 341, "story": 342, "place": 343, "@time": 344, "@dailymail": 345, "life": 346, "free": 347, "@tedcruz": 348, "@ingrahamangle": 349, "trying": 350, "paris": 351, "@historicalpics": 352, "@foxla": 353, "war": 354, "old": 355, "since": 356, "two": 357, "she's": 358, "care": 359, "else": 360, "cnn": 361, "wonder": 362, "breaking": 363, "donald": 364, "family": 365, "last": 366, "photo": 367, "away": 368, "@flotus": 369, "sydney": 370, "flag": 371, "hate": 372, "wait": 373, "today": 374, ";": 375, "jobs": 376, "refugees": 377, "pope": 378, "lot": 379, "@bernlennials": 380, "children": 381, "long": 382, "saying": 383, "wtf": 384, "3": 385, "agree": 386, "sick": 387, "@snopes": 388, "ppl": 389, "joke": 390, "wants": 391, "change": 392, "sorry": 393, "nhttps": 394, "lying": 395, "year": 396, "let's": 397, "shooting": 398, "@latimes": 399, "won": 400, "until": 401, "dog": 402, "name": 403, "getting": 404, "food": 405, "things": 406, "@allenwest": 407, "point": 408, "guys": 409, "colors": 410, "million": 411, "ok": 412, "nice": 413, "talking": 414, "happen": 415, "@presssec": 416, "talk": 417, "call": 418, "#": 419, "@complexmag": 420, "fuck": 421, "home": 422, "potus": 423, "around": 424, "@stephenfhayes": 425, "@walshfreedom": 426, "@abc7": 427, "heard": 428, "sanders": 429, "shot": 430, "find": 431, "hostage": 432, "little": 433, "mr": 434, "list": 435, "send": 436, "start": 437, "@finessehaven": 438, "terrorist": 439, "less": 440, "coming": 441, "@ajplus": 442, "@hunterschwarz": 443, "@coslive": 444, "days": 445, "@wsjpolitics": 446, "problem": 447, "least": 448, "@tvguide": 449, "check": 450, "disgusting": 451, "end": 452, "there's": 453, "both": 454, "government": 455, "cafe": 456, "boycott": 457, "far": 458, "poor": 459, "ago": 460, "lost": 461, "making": 462, "pretty": 463, "safe": 464, "party": 465, "left": 466, "tweet": 467, "happy": 468, "red": 469, "tax": 470, "truth": 471, "ass": 472, "@thelastrefuge2": 473, "@yahoonews": 474, "person": 475, "=": 476, "@christiec733": 477, "@peddoc63": 478, "omg": 479, "matter": 480, "\u2026": 481, "remember": 482, "abortion": 483, "@people4bernie": 484, "seen": 485, "@piersmorgan": 486, "@ninaturner": 487, "punishment": 488, "part": 489, "10": 490, "@cnnwire": 491, "water": 492, "crazy": 493, "might": 494, "run": 495, "kids": 496, "gets": 497, "racist": 498, "kill": 499, "poll": 500, "@anncoulter": 501, "game": 502, "wouldn't": 503, "fake": 504, "beautiful": 505, "control": 506, "called": 507, "@breakingnews": 508, "b": 509, "feel": 510, "rest": 511, "aren't": 512, "attack": 513, "bathroom": 514, "funny": 515, "damn": 516, "$reserved$": 517, "once": 518, "having": 519, "times": 520, "hard": 521, "race": 522, "#sydneysiege": 523, "@lucyflores": 524, "wasn't": 525, "either": 526, "follow": 527, "taking": 528, "seems": 529, "though": 530, "#breaking": 531, "political": 532, "whole": 533, "@nbcnews": 534, "@gawker": 535, "reason": 536, "crap": 537, "gop": 538, "funeral": 539, "t": 540, "others": 541, "happened": 542, "parliament": 543, "@prisonplanet": 544, "illegal": 545, "course": 546, "5": 547, "sounds": 548, "issue": 549, "iran": 550, "ruling": 551, "powell": 552, "sense": 553, "try": 554, "public": 555, "idiots": 556, "bet": 557, "lit": 558, "buy": 559, "source": 560, "blame": 561, "i've": 562, "states": 563, "shame": 564, "@madisonbeer": 565, "court": 566, "gonna": 567, "\ufe0f": 568, "everything": 569, "cares": 570, "cover": 571, "hear": 572, "mass": 573, "@andieiamwhoiam": 574, "without": 575, "@petesouza": 576, "top": 577, "rights": 578, "@libertyusa1776": 579, "surprised": 580, "king": 581, "evil": 582, "kind": 583, "child": 584, "word": 585, "history": 586, "muslims": 587, "security": 588, "@kfc": 589, "@barackobama": 590, "article": 591, "report": 592, "@telegraphnews": 593, "picture": 594, "@cernovich": 595, "looking": 596, "religion": 597, "few": 598, "goes": 599, "@foxnewsinsider": 600, "used": 601, "liar": 602, "@afp": 603, "knew": 604, "paid": 605, "death": 606, "hrc": 607, "human": 608, "policy": 609, "father": 610, "national": 611, "shootings": 612, "killing": 613, "democrat": 614, "face": 615, "8": 616, "seriously": 617, "ask": 618, "instead": 619, "hey": 620, "@mailonline": 621, "@slate": 622, "during": 623, "cause": 624, "words": 625, "amazing": 626, "freed": 627, "mind": 628, "fucking": 629, "+": 630, "candidate": 631, "working": 632, "#charliehebdo": 633, "@robdelaney": 634, "smh": 635, "@dloesch": 636, "number": 637, "kim": 638, "@drmartyfox": 639, "stand": 640, "taken": 641, "15": 642, "ur": 643, "thats": 644, "health": 645, "understand": 646, "idea": 647, "@cnnmoney": 648, "davis": 649, "democrats": 650, "@xojanedotcom": 651, "held": 652, "high": 653, "young": 654, "hill": 655, "12": 656, "lives": 657, "full": 658, "@tchopstl": 659, "islamic": 660, "lights": 661, "late": 662, "cruz": 663, "bs": 664, "stay": 665, "@mostobviousfact": 666, "bit": 667, "i'll": 668, "act": 669, "@bretbaier": 670, "terrorists": 671, "@instyle": 672, "china": 673, "hitler": 674, "question": 675, "paying": 676, "4d": 677, "republican": 678, "rip": 679, "fox": 680, "@savetheanimais": 681, "liberal": 682, "gone": 683, "wish": 684, "bullshit": 685, "went": 686, "udd": 687, "@nickkristof": 688, "fact": 689, "cool": 690, "we're": 691, "deal": 692, "eat": 693, "took": 694, "@pzf": 695, "@blisstabitha": 696, "laws": 697, "finally": 698, "low": 699, "islam": 700, "using": 701, "died": 702, "inside": 703, "@chuckwoolery": 704, "campaign": 705, "ridiculous": 706, "6": 707, "lmao": 708, "exactly": 709, "holy": 710, "fbi": 711, "@mtv": 712, "post": 713, "@dailycaller": 714, "leave": 715, "shop": 716, "light": 717, "shouldn't": 718, "peace": 719, "@repmialove": 720, "@gamma_ray239": 721, "play": 722, ":)": 723, "7": 724, "syrian": 725, "video": 726, "c": 727, "celebrate": 728, "i'd": 729, "respect": 730, "@nypost": 731, "@johnatsrs1949": 732, "office": 733, "move": 734, "fired": 735, "school": 736, "shooter": 737, "@scegielskipr": 738, "4f": 739, "set": 740, "means": 741, "tv": 742, "facts": 743, "christians": 744, "through": 745, "heart": 746, "thinking": 747, "siege": 748, "told": 749, "@starbucks": 750, "couldn't": 751, "shows": 752, "bush": 753, "due": 754, "knows": 755, "@paisleytigerco": 756, "head": 757, "burger": 758, "stock": 759, ":(": 760, "@justthatguyben": 761, "100": 762, "o": 763, "awesome": 764, "11": 765, "close": 766, "answer": 767, "@who": 768, "different": 769, "@telegraph": 770, "surprise": 771, "via": 772, "group": 773, "parents": 774, "ones": 775, "situation": 776, "charlie": 777, "decision": 778, "saw": 779, "dems": 780, "@rawstory": 781, "@empiremagazine": 782, "idiot": 783, "14": 784, "christian": 785, "private": 786, "liberals": 787, "common": 788, "2016": 789, "ya": 790, "absolutely": 791, "open": 792, "numbers": 793, "@thedemocrats": 794, "@israelinusa": 795, "hit": 796, "himself": 797, "@freebeacon": 798, "important": 799, "uk": 800, "\u2764": 801, "dont": 802, "class": 803, "business": 804, "@jaycaruso": 805, "elected": 806, "hebdo": 807, "debate": 808, "canada": 809, "worse": 810, "d": 811, "reports": 812, "running": 813, "except": 814, "@skynews": 815, "equal": 816, "@bipartisanism": 817, "comes": 818, "arrested": 819, "met": 820, "@wcvi": 821, "reagan": 822, "horrible": 823, "nation": 824, "proud": 825, "20": 826, "twitter": 827, "dangerous": 828, "kidding": 829, "#lovewins": 830, "@cbsnews": 831, "stuff": 832, "supporters": 833, "case": 834, "nobody": 835, "politics": 836, "totally": 837, "@michelle4trump": 838, "@mydaughtersarmy": 839, "boy": 840, "rather": 841, "@johnrlottjr": 842, "several": 843, "@theobserver": 844, "freedom": 845, "found": 846, "book": 847, "tonight": 848, "@realbencarson": 849, "udf": 850, "meet": 851, "supermarket": 852, "@nycjim": 853, "special": 854, "glad": 855, "nancy": 856, "expect": 857, "turn": 858, "trust": 859, "lied": 860, "interesting": 861, "transgender": 862, "alone": 863, "themselves": 864, "folks": 865, "month": 866, "socialist": 867, "soldier": 868, "takes": 869, "happens": 870, "obama's": 871, "able": 872, "future": 873, "created": 874, "@callisto1947": 875, "giving": 876, "40": 877, "2d": 878, "lose": 879, "2015": 880, "info": 881, "countries": 882, "@khaledbeydoun": 883, "qb": 884, "statement": 885, "la": 886, "cam": 887, "christmas": 888, "@ap_politics": 889, "em": 890, "military": 891, "order": 892, "soon": 893, "votes": 894, "nevada": 895, "etc": 896, "economy": 897, "meat": 898, "earth": 899, "needed": 900, "behind": 901, "plan": 902, "jail": 903, "0d": 904, "voting": 905, "riding": 906, "uddf": 907, "forget": 908, "haven't": 909, "waiting": 910, "mouth": 911, "came": 912, "#trump": 913, "bring": 914, "@thepatriot143": 915, "gave": 916, "continue": 917, "@": 918, "equality": 919, "super": 920, "blue": 921, "past": 922, "charge": 923, "false": 924, "millions": 925, "anyway": 926, "dogs": 927, "de": 928, "power": 929, "church": 930, "marijuana": 931, "@pzfeed": 932, "bag": 933, "martin": 934, "correct": 935, "worst": 936, "reporting": 937, "lets": 938, "save": 939, "@nytvideo": 940, "criminal": 941, "@onceabc": 942, "lead": 943, "racism": 944, "couple": 945, "son": 946, "caught": 947, "south": 948, "sex": 949, "form": 950, "terrible": 951, "@humanitycritic": 952, "@theliluminati": 953, "telling": 954, "@teamusa": 955, "fast": 956, "@dbongino": 957, "each": 958, "dumb": 959, "issues": 960, "gov": 961, "watching": 962, "fault": 963, "fire": 964, "blacks": 965, "1st": 966, "election": 967, "@clickhole": 968, "difference": 969, "employees": 970, "@kredo0": 971, "stopped": 972, "@talkopan": 973, "wife": 974, "brought": 975, "legal": 976, "according": 977, "murder": 978, "bbc": 979, "asked": 980, "united": 981, "uddfa": 982, "roof": 983, "dylann": 984, "koran": 985, "wanted": 986, "@theeconomist": 987, "trump's": 988, "@cbcalerts": 989, "huh": 990, "@colinodonoghue1": 991, "system": 992, "become": 993, "9": 994, "possible": 995, "ottawa": 996, "citizens": 997, "f": 998, "supreme": 999, "@afpphoto": 1000, "attend": 1001, "shoot": 1002, "voters": 1003, "french": 1004, "thinks": 1005, "canadian": 1006, "drug": 1007, "jesus": 1008, "side": 1009, "fight": 1010, "prayers": 1011, "crime": 1012, "starbucks": 1013, "@chrisloesch": 1014, "33": 1015, "kid": 1016, "pathetic": 1017, "attention": 1018, "small": 1019, "whatever": 1020, "@pagesixemily": 1021, "three": 1022, "town": 1023, "actual": 1024, "night": 1025, "@guypbenson": 1026, "disgrace": 1027, "pass": 1028, "@conservativeind": 1029, "works": 1030, "living": 1031, "short": 1032, "friends": 1033, "bought": 1034, "germany": 1035, "worry": 1036, "corruption": 1037, "violence": 1038, "jewish": 1039, "half": 1040, "sign": 1041, "congress": 1042, "pres": 1043, "line": 1044, "pic": 1045, "delegates": 1046, "headline": 1047, "gunman": 1048, "fine": 1049, "share": 1050, "@chriskofinis": 1051, "girl": 1052, "ted": 1053, "cut": 1054, "prison": 1055, "near": 1056, "chance": 1057, "vegetarians": 1058, "middle": 1059, "@wsj": 1060, "force": 1061, "doubt": 1062, "who's": 1063, "republicans": 1064, "somebody": 1065, "gives": 1066, "confirmed": 1067, "happening": 1068, "suspect": 1069, "lady": 1070, "site": 1071, "wake": 1072, "actions": 1073, ">": 1074, "#feelthebern": 1075, "color": 1076, "problems": 1077, "@jennagiesta": 1078, "five": 1079, "arrest": 1080, "@trump_world": 1081, "@lauderdaleagent": 1082, "@pagesix": 1083, "mention": 1084, "justice": 1085, "miss": 1086, "donations": 1087, "21": 1088, "@rt_com": 1089, "team": 1090, "based": 1091, "destroy": 1092, "ain't": 1093, "pray": 1094, "y": 1095, "dhs": 1096, "almost": 1097, "terrorism": 1098, "complete": 1099, "ready": 1100, "@instapundit": 1101, "faith": 1102, "crimes": 1103, "definitely": 1104, "brain": 1105, "ni": 1106, "unbelievable": 1107, "showing": 1108, "meeting": 1109, "ahead": 1110, "@holocaustmuseum": 1111, "shameful": 1112, "01": 1113, "oath": 1114, "cannot": 1115, "@sandraaltx": 1116, "hand": 1117, "obviously": 1118, "hands": 1119, "europe": 1120, "@mehreenzahra": 1121, "event": 1122, "shots": 1123, "@fact": 1124, "#afp": 1125, "mother": 1126, "@daveweasel": 1127, "hungry": 1128, "wh": 1129, "imagine": 1130, "@vp": 1131, "comments": 1132, "sports": 1133, "link": 1134, "@greysabc": 1135, "huge": 1136, "corrupt": 1137, "self": 1138, "30": 1139, "leader": 1140, "\u2014": 1141, "pride": 1142, "yea": 1143, "total": 1144, "kkk": 1145, "steve": 1146, "presidential": 1147, "@lindasuhler": 1148, "@meredithfrost": 1149, "gold": 1150, "vatican": 1151, "worth": 1152, "questions": 1153, "honor": 1154, "together": 1155, "shut": 1156, "people's": 1157, "hold": 1158, "drink": 1159, "72": 1160, "@cbseveningnews": 1161, "room": 1162, "likely": 1163, "especially": 1164, "#trump2016": 1165, "haha": 1166, "given": 1167, "22": 1168, "girls": 1169, "truly": 1170, "supposed": 1171, "single": 1172, "@waynedupreeshow": 1173, "credit": 1174, "religious": 1175, "amen": 1176, "started": 1177, "walk": 1178, "nonsense": 1179, "@dailynewsbin": 1180, "ban": 1181, "turned": 1182, "clear": 1183, "syria": 1184, "anymore": 1185, "@scottbaio": 1186, "@penguinsfan62": 1187, "service": 1188, "visit": 1189, "surprising": 1190, "bless": 1191, "updates": 1192, "im": 1193, "medical": 1194, "bunch": 1195, "calling": 1196, "dollars": 1197, "winning": 1198, "taxes": 1199, "evidence": 1200, "billion": 1201, "bill": 1202, "gotta": 1203, "|": 1204, "50": 1205, "bags": 1206, "terror": 1207, "governor": 1208, "polls": 1209, "seem": 1210, "pick": 1211, "protect": 1212, "@th3j35t3r": 1213, "nhttp": 1214, "administration": 1215, "admit": 1216, "research": 1217, "clearly": 1218, "civil": 1219, "letter": 1220, "allowed": 1221, "reported": 1222, "@timenout": 1223, "coverage": 1224, "alive": 1225, "completely": 1226, "add": 1227, "@funnypicsdepot": 1228, "email": 1229, "fit": 1230, "along": 1231, "thoughts": 1232, "dem": 1233, "known": 1234, "age": 1235, "@wntonight": 1236, "street": 1237, "easy": 1238, "okay": 1239, "community": 1240, "including": 1241, "build": 1242, "college": 1243, "afraid": 1244, "speak": 1245, "5p": 1246, "piece": 1247, "choose": 1248, "agenda": 1249, "choice": 1250, "colin": 1251, "comment": 1252, "putin": 1253, "politicians": 1254, "secret": 1255, "families": 1256, "dad": 1257, "step": 1258, "@washingtonpost": 1259, "france": 1260, "learn": 1261, "responsible": 1262, "count": 1263, "thomas": 1264, "assault": 1265, "convention": 1266, "die": 1267, "constitution": 1268, "double": 1269, "account": 1270, "@stonewall_77": 1271, "serious": 1272, "que": 1273, "voted": 1274, "quite": 1275, "he'll": 1276, "rally": 1277, "@theblaze": 1278, "refugee": 1279, "between": 1280, "allow": 1281, "weapons": 1282, "wage": 1283, "@io9": 1284, "hasn't": 1285, "social": 1286, "nude": 1287, "smart": 1288, "release": 1289, "week": 1290, "views": 1291, "victims": 1292, "song": 1293, "google": 1294, "official": 1295, "entire": 1296, "el": 1297, "morning": 1298, "wall": 1299, "kfc": 1300, "@coloradogun": 1301, "propaganda": 1302, "foreign": 1303, "bob": 1304, "born": 1305, "fall": 1306, "sir": 1307, "worked": 1308, "@npr": 1309, "normal": 1310, "bomb": 1311, "uber": 1312, "shopping": 1313, "armed": 1314, "prove": 1315, "press": 1316, "north": 1317, "eh": 1318, "horrific": 1319, "trumps": 1320, "samson": 1321, "misleading": 1322, "sickening": 1323, "hmmm": 1324, "excuse": 1325, "pissed": 1326, "planet": 1327, "@pennjillette": 1328, "insane": 1329, "murdoch": 1330, "tells": 1331, "udffb": 1332, "wins": 1333, "magazine": 1334, "@veteran4trump": 1335, "#boycotttarget": 1336, "tried": 1337, "god's": 1338, "longer": 1339, "wearing": 1340, "apparently": 1341, "air": 1342, "gender": 1343, "@fox59": 1344, "realize": 1345, "yep": 1346, "you've": 1347, "record": 1348, "scotus": 1349, "scary": 1350, "following": 1351, "female": 1352, "apology": 1353, "fan": 1354, "enemy": 1355, "@ericbradner": 1356, "biological": 1357, "desperate": 1358, "@thexfiles": 1359, "hahaha": 1360, "opinion": 1361, "@batmanvsuperman": 1362, "@historyinpix": 1363, "#crookedhillary": 1364, "boyfriend": 1365, "oil": 1366, "gunmen": 1367, "@jimeastridge1": 1368, "simply": 1369, "hmm": 1370, "trouble": 1371, "drunk": 1372, "notice": 1373, "@snoopdogg": 1374, "none": 1375, "non": 1376, "cant": 1377, "louisiana": 1378, "emails": 1379, "e": 1380, "beyond": 1381, "@cnnent": 1382, "chicken": 1383, "attacks": 1384, "where's": 1385, "christ": 1386, "um": 1387, "@cia": 1388, "cute": 1389, "eye": 1390, "@mullane45": 1391, "everybody": 1392, "\u2018": 1393, "land": 1394, "perfect": 1395, "weird": 1396, "per": 1397, "peaceful": 1398, "@cloydrivers": 1399, "coach": 1400, "welcome": 1401, "dirty": 1402, "@ledbettercarly": 1403, "mad": 1404, "male": 1405, "market": 1406, "@theweeknd": 1407, "level": 1408, "company": 1409, "conservative": 1410, "context": 1411, "cops": 1412, "investigation": 1413, "democratic": 1414, "crooked": 1415, "@christinawilkie": 1416, "@johnfund": 1417, "@worstfact": 1418, "former": 1419, "lord": 1420, "medals": 1421, "hero": 1422, "hot": 1423, "@globeandmail": 1424, "fear": 1425, "example": 1426, "16": 1427, "18": 1428, "period": 1429, "feed": 1430, "@nytnational": 1431, "plastic": 1432, "playing": 1433, "baby": 1434, "@guardiannews": 1435, "@ericbolling": 1436, "presidents": 1437, "pictures": 1438, "blood": 1439, "@ufc": 1440, "fighting": 1441, "memorial": 1442, "friend": 1443, "chicago": 1444, "mental": 1445, "missing": 1446, "mom": 1447, "certainly": 1448, "months": 1449, "25": 1450, "focus": 1451, "@twcbreaking": 1452, "nthe": 1453, "building": 1454, "nv": 1455, "en": 1456, "hours": 1457, "@johnggalt": 1458, "korea": 1459, "sent": 1460, "tho": 1461, "#obama": 1462, "society": 1463, "ud83e": 1464, "vs": 1465, "suspected": 1466, "selfie": 1467, "soldiers": 1468, "#tcot": 1469, "waste": 1470, "walmart": 1471, "unless": 1472, "scared": 1473, "ladies": 1474, ":\\": 1475, "0": 1476, "leaders": 1477, "pos": 1478, "defend": 1479, "spreading": 1480, "95": 1481, "experience": 1482, "adopted": 1483, "response": 1484, "pee": 1485, "update": 1486, "soul": 1487, "stairs": 1488, "eyes": 1489, "presidency": 1490, "today's": 1491, "illustrated": 1492, "supports": 1493, "@realalexjones": 1494, "surely": 1495, "sweet": 1496, "13": 1497, "hair": 1498, "schools": 1499, "fair": 1500, "re": 1501, "iranian": 1502, "straight": 1503, "front": 1504, "jenner": 1505, "fool": 1506, "yourself": 1507, "clinton's": 1508, "finds": 1509, "golf": 1510, "plane": 1511, "~": 1512, "claim": 1513, "bro": 1514, "body": 1515, "chief": 1516, "chris": 1517, "break": 1518, "city": 1519, "carson": 1520, "celebrating": 1521, "hillary's": 1522, "simple": 1523, "@skynewsaust": 1524, "m": 1525, "major": 1526, "asking": 1527, ";)": 1528, "@seanhannity": 1529, "ha": 1530, "@skynewsbreak": 1531, "reagan's": 1532, "spend": 1533, "gays": 1534, "camp": 1535, "iraq": 1536, "loved": 1537, "shocking": 1538, "same-sex": 1539, "@cp24": 1540, "east": 1541, "growth": 1542, "proof": 1543, "west": 1544, "treated": 1545, "bc": 1546, "typical": 1547, "beat": 1548, "@_hankrearden": 1549, "latino": 1550, "govt": 1551, "establishment": 1552, "served": 1553, "higher": 1554, "california": 1555, "increase": 1556, "abuse": 1557, "innocent": 1558, "anybody": 1559, "skip": 1560, "fucked": 1561, "candidates": 1562, "#isis": 1563, "quit": 1564, "confirm": 1565, "#neverhillary": 1566, "jindal": 1567, "keeps": 1568, "mess": 1569, "@fxnleisure": 1570, "photos": 1571, "animals": 1572, "ride": 1573, "forever": 1574, "action": 1575, "threat": 1576, "supporter": 1577, "minister": 1578, "refuse": 1579, "weak": 1580, "prisons": 1581, "speech": 1582, "county": 1583, "supporting": 1584, "forced": 1585, "cost": 1586, "forward": 1587, "accident": 1588, "return": 1589, "@independent": 1590, "insurance": 1591, "mt": 1592, "changed": 1593, "enter": 1594, "dude": 1595, "msm": 1596, "background": 1597, "released": 1598, "@capehartj": 1599, "figure": 1600, "test": 1601, "k": 1602, "sky": 1603, "@cbcnews": 1604, "explain": 1605, "moving": 1606, "francis": 1607, "lack": 1608, "@carminezozzora": 1609, "everywhere": 1610, "stories": 1611, "price": 1612, "third": 1613, "foods": 1614, "latest": 1615, "moment": 1616, "killer": 1617, "helping": 1618, "confederate": 1619, "raise": 1620, "decide": 1621, "debt": 1622, "hilarious": 1623, "daughter": 1624, "data": 1625, "belief": 1626, "ignorant": 1627, "seeing": 1628, "sharing": 1629, "luck": 1630, "talks": 1631, "cuz": 1632, "curious": 1633, "@schwarzenegger": 1634, "radical": 1635, "cup": 1636, "pattern": 1637, "immigrants": 1638, "@khanoisseur": 1639, "homeless": 1640, "personal": 1641, "honest": 1642, "rules": 1643, "hopefully": 1644, "#opkkk": 1645, "@uber_sydney": 1646, "marry": 1647, "anti": 1648, "@toddstarnes": 1649, "clintons": 1650, "hurt": 1651, "zone": 1652, "@markgatiss": 1653, "#blacklivesmatter": 1654, "pics": 1655, "sound": 1656, "names": 1657, "disgraceful": 1658, "asparagus": 1659, "written": 1660, "here's": 1661, "bull": 1662, "charles": 1663, "@richlowry": 1664, "spread": 1665, "@spurs": 1666, "dick": 1667, "herself": 1668, "write": 1669, "missed": 1670, "beckel": 1671, "rich": 1672, "space": 1673, "strange": 1674, "boycotting": 1675, "however": 1676, "car": 1677, "points": 1678, "virus": 1679, "@stationcdrkelly": 1680, "women's": 1681, "rate": 1682, "information": 1683, "stupidity": 1684, "obvious": 1685, "gunmen's": 1686, "pure": 1687, "suspects": 1688, "murdered": 1689, "officer": 1690, "study": 1691, "hi": 1692, "strong": 1693, "@enews": 1694, "term": 1695, "rudy": 1696, "glass": 1697, "server": 1698, "immediately": 1699, "reality": 1700, "nope": 1701, "nthis": 1702, "claims": 1703, "exist": 1704, "nooo": 1705, "loss": 1706, "population": 1707, "local": 1708, "politically": 1709, "cheating": 1710, "#superman": 1711, "deaths": 1712, "libs": 1713, "pose": 1714, "weeks": 1715, "throw": 1716, "pricing": 1717, "@bullitino": 1718, "drivers": 1719, "disney": 1720, "dropped": 1721, "#ottawa": 1722, "un": 1723, "message": 1724, "@limerick1914": 1725, "sell": 1726, "congrats": 1727, "natural": 1728, "speaking": 1729, "44": 1730, "bigots": 1731, "pc": 1732, "criminals": 1733, "restroom": 1734, "cross": 1735, "sadly": 1736, "crow": 1737, "abortions": 1738, "sun": 1739, "donate": 1740, "08": 1741, "attempt": 1742, "eating": 1743, "outside": 1744, "y'all": 1745, "stick": 1746, "faces": 1747, "orleans": 1748, "catch": 1749, "labor": 1750, "excellent": 1751, "@chairmnoomowmow": 1752, "judge": 1753, "stats": 1754, "eu": 1755, "espn": 1756, "@thextrumpxtrain": 1757, "@who_europe": 1758, "florida": 1759, "john": 1760, "above": 1761, "al": 1762, "tiger": 1763, "#cdnpoli": 1764, "federal": 1765, "strategist": 1766, "join": 1767, "matters": 1768, "southern": 1769, "michael": 1770, "image": 1771, "married": 1772, "isla": 1773, "interested": 1774, "29": 1775, "lazy": 1776, "leading": 1777, "lawyers": 1778, "@politicsnewz": 1779, "leaving": 1780, "laughing": 1781, "standing": 1782, "standard": 1783, "prince": 1784, "noticed": 1785, "aid": 1786, "liking": 1787, "african": 1788, "moon": 1789, "amount": 1790, "@classicpict": 1791, "negative": 1792, "majority": 1793, "sometimes": 1794, "humans": 1795, "4e": 1796, "fish": 1797, "awful": 1798, "expected": 1799, "satirical": 1800, "perhaps": 1801, "tough": 1802, "ways": 1803, "pop": 1804, "consider": 1805, "@pundamentalism": 1806, "@tomangell": 1807, "#wakeupamerica": 1808, "board": 1809, "@whoafro": 1810, "openly": 1811, "fisher": 1812, "they'll": 1813, "babies": 1814, "enjoy": 1815, "@sharrimarkson": 1816, "8\\": 1817, "udffc": 1818, "@jonathanky74": 1819, "dear": 1820, "twice": 1821, "satan": 1822, "don": 1823, "position": 1824, "believes": 1825, "#scotus": 1826, "drugs": 1827, "education": 1828, "ben": 1829, "humanity": 1830, "games": 1831, "deserves": 1832, "general": 1833, "carry": 1834, "@nro": 1835, "catholic": 1836, "@rt_america": 1837, "sending": 1838, "4c": 1839, "hilary": 1840, "#makeamericagreatagain": 1841, "powerful": 1842, "round": 1843, "greatest": 1844, "holding": 1845, "@_happy_gilmore": 1846, "boys": 1847, "hoping": 1848, "@worldbank": 1849, "argument": 1850, "@dbargen": 1851, "responsibility": 1852, "cars": 1853, "seizure": 1854, "carrying": 1855, "94": 1856, "@senatorreid": 1857, "beliefs": 1858, "socialism": 1859, "spin": 1860, "cups": 1861, "customers": 1862, "caitlyn": 1863, "80": 1864, "passed": 1865, "london": 1866, "bus": 1867, "@scrowder": 1868, "prime": 1869, "minute": 1870, "christianity": 1871, "31": 1872, "sony": 1873, "michelle": 1874, "v": 1875, "somewhere": 1876, "chickens": 1877, "charity": 1878, "chapo": 1879, "mistake": 1880, "udca": 1881, "#paris": 1882, "clubs": 1883, "bloody": 1884, "rid": 1885, "60": 1886, "companies": 1887, "concerned": 1888, "caused": 1889, "zero": 1890, "nature": 1891, "we've": 1892, "@richardlochhead": 1893, "cash": 1894, "plenty": 1895, "mentioned": 1896, "anonymous": 1897, "@jammiewf": 1898, "reportedly": 1899, "feels": 1900, "saudi": 1901, "listen": 1902, "original": 1903, "@rebootliberty": 1904, "assume": 1905, "@youranonnews": 1906, "four": 1907, "allah": 1908, "reasons": 1909, "fun": 1910, "jandali": 1911, "@whosearo": 1912, "@9newssyd": 1913, "involved": 1914, "november": 1915, "guard": 1916, "h": 1917, "instagram": 1918, "@winterxlarrys": 1919, "industry": 1920, "syndrome": 1921, "putting": 1922, "suppose": 1923, "honestly": 1924, "racial": 1925, "supported": 1926, "kept": 1927, "09": 1928, "whether": 1929, "@pahowho": 1930, "selling": 1931, "agreed": 1932, "staff": 1933, "dies": 1934, "@mscott": 1935, "bathrooms": 1936, "second": 1937, "sales": 1938, "killary": 1939, "yr": 1940, "leadership": 1941, "dr": 1942, "escalators": 1943, "registered": 1944, "@guardian": 1945, "provide": 1946, "large": 1947, "executive": 1948, "trash": 1949, "avoid": 1950, "@whoemro": 1951, "@variety": 1952, "nuts": 1953, "@thr": 1954, "you'll": 1955, "sleep": 1956, "sitting": 1957, "abdulfattah": 1958, "#scotusmarriage": 1959, "abc": 1960, "officials": 1961, "p": 1962, "nor": 1963, "@wildpipm": 1964, "yay": 1965, "pledge": 1966, "@pontifex": 1967, "onion": 1968, "@robboma3": 1969, "music": 1970, "damage": 1971, "dare": 1972, "@joerogan": 1973, "delegate": 1974, "democracy": 1975, "bed": 1976, "deserve": 1977, "tweets": 1978, "basketball": 1979, "wear": 1980, "doctor": 1981, "banned": 1982, "drop": 1983, "earn": 1984, "escaped": 1985, "@heritage": 1986, "@natshupe": 1987, "australia": 1988, "fed": 1989, "feeling": 1990, "door": 1991, "@justintrudeau": 1992, "crisis": 1993, "bern": 1994, "bravo": 1995, "voice": 1996, "buying": 1997, "card": 1998, "victim": 1999, "cases": 2000, "chelsea": 2001, "washington": 2002, "classless": 2003, "clean": 2004, "@leahr77": 2005, "clown": 2006, "blind": 2007, "@lagartija_nix": 2008, "blaming": 2009, "wave": 2010, "@miselizajane": 2011, "controller": 2012, "bible": 2013, "create": 2014, "creating": 2015, "timing": 2016, "myself": 2017, "till": 2018, "fix": 2019, "iowa": 2020, "isnt": 2021, "stores": 2022, "store": 2023, "jews": 2024, "journalism": 2025, "@causewereguys": 2026, "l": 2027, "starve": 2028, "interview": 2029, "letting": 2030, "lower": 2031, "@bimmerella": 2032, "wth": 2033, "speaks": 2034, "meaning": 2035, "meant": 2036, "medal": 2037, "minimum": 2038, "ms": 2039, "@bradthor": 2040, "internet": 2041, "incredible": 2042, "@cwthe100": 2043, "fly": 2044, "foot": 2045, "assassination": 2046, "they've": 2047, "funerals": 2048, "garbage": 2049, "geographic": 2050, "global": 2051, "green": 2052, "grew": 2053, "gross": 2054, "winner": 2055, "@drewgrimaldi": 2056, "apple": 2057, "appears": 2058, "he'd": 2059, "heads": 2060, "surge": 2061, "hoax": 2062, "horse": 2063, "ill": 2064, "@gb_ball": 2065, "hide": 2066, "indeed": 2067, "0f": 2068, "pushing": 2069, "restaurant": 2070, "politician": 2071, "37": 2072, "23": 2073, "quote": 2074, "0a": 2075, "reading": 2076, "safety": 2077, "4a": 2078, "#usa": 2079, "relevant": 2080, "@talkmaster": 2081, "3rd": 2082, "serve": 2083, "policies": 2084, "\u2013": 2085, "expensive": 2086, "microsoft": 2087, "page": 2088, "michigan": 2089, "yrs": 2090, "shocked": 2091, "load": 2092, "result": 2093, "\u00a3": 2094, "<": 2095, "crying": 2096, "@deray": 2097, "dark": 2098, "racists": 2099, "outrage": 2100, "accurate": 2101, ":d": 2102, "99": 2103, "merkel": 2104, "sue": 2105, "75": 2106, "pays": 2107, "streets": 2108, "russian": 2109, "usual": 2110, "matthews": 2111, "workers": 2112, "punish": 2113, "@pethillbecky": 2114, "wasting": 2115, "@unodc": 2116, "america's": 2117, "confirms": 2118, "acts": 2119, "conservatives": 2120, "members": 2121, "among": 2122, "mentally": 2123, "continues": 2124, "sort": 2125, "returns": 2126, "mercy": 2127, "copy": 2128, "hiding": 2129, "paper": 2130, "animal": 2131, "ap": 2132, "heartbreaking": 2133, "@dlynaffor": 2134, "football": 2135, "neither": 2136, "similar": 2137, "balls": 2138, "@wonderella": 2139, "dying": 2140, "followers": 2141, "flint": 2142, "eagle": 2143, "#gop": 2144, "early": 2145, "weren't": 2146, "embarrassing": 2147, "lmfao": 2148, "energy": 2149, "@zerohedge": 2150, "tony": 2151, "@ajam": 2152, "australian": 2153, "et": 2154, "yesterday": 2155, "tragedy": 2156, "expose": 2157, "welfare": 2158, "forces": 2159, "forgot": 2160, "@thedailybeast": 2161, "@armedresearch": 2162, "heaven": 2163, "45": 2164, "becomes": 2165, "website": 2166, "reporters": 2167, "destroyed": 2168, "handle": 2169, "appropriate": 2170, "guilty": 2171, "pot": 2172, "prez": 2173, "weed": 2174, "didnt": 2175, "dignity": 2176, "grocery": 2177, "olympic": 2178, "disrespectful": 2179, "willing": 2180, "na": 2181, "dollar": 2182, "further": 2183, "nba": 2184, "fraud": 2185, "@econbizfin": 2186, "worried": 2187, "results": 2188, "praying": 2189, "joe": 2190, "wanna": 2191, "brilliant": 2192, "lovely": 2193, "choices": 2194, "@marksimoneny": 2195, "losing": 2196, "24": 2197, "looked": 2198, "lindt": 2199, "loving": 2200, "changes": 2201, "btw": 2202, "46": 2203, "judicial": 2204, "played": 2205, "star": 2206, "kick": 2207, "lue": 2208, "kerry": 2209, "@maestrouzy": 2210, "stage": 2211, "standards": 2212, "ceo": 2213, "carolina": 2214, "starts": 2215, "capitalism": 2216, "lines": 2217, "starting": 2218, "kosher": 2219, "brother": 2220, "plans": 2221, "stabs": 2222, "machine": 2223, "@buzzfeednews": 2224, "spine": 2225, "kinda": 2226, "afford": 2227, "planned": 2228, "prices": 2229, "morons": 2230, "moron": 2231, "@pamelageller": 2232, "deny": 2233, "witch": 2234, "solitary": 2235, "caucus": 2236, "date": 2237, "flood": 2238, "careful": 2239, "sandwich": 2240, "daughters": 2241, "@tommy_xpensive": 2242, "deep": 2243, "possibly": 2244, "afp": 2245, "defending": 2246, "lucky": 2247, "sentence": 2248, "@libertybell1000": 2249, "ugh": 2250, "protest": 2251, "anywhere": 2252, "@politifact": 2253, "remains": 2254, "@carolinemarcus": 2255, "earlier": 2256, "statistics": 2257, "begin": 2258, "@nydailynews": 2259, "oops": 2260, "network": 2261, "nah": 2262, "absolute": 2263, "scandal": 2264, "#japan": 2265, "nand": 2266, "gas": 2267, "officially": 2268, "narrative": 2269, "row": 2270, "gamecube": 2271, "gain": 2272, "donated": 2273, "@willmcavoyacn": 2274, "nathan": 2275, "@americanfamassc": 2276, "nations": 2277, "downtown": 2278, "10,000": 2279, "freaking": 2280, "nbd": 2281, "thousand": 2282, "calls": 2283, "pin": 2284, "arms": 2285, "tennessee": 2286, "rat": 2287, "movie": 2288, "voter": 2289, "@rogerjstonejr": 2290, "@nprpolitics": 2291, "fools": 2292, "op": 2293, "0e": 2294, "cancels": 2295, "learned": 2296, "online": 2297, "grow": 2298, "grouper": 2299, "disagree": 2300, "@angus_ol": 2301, "area": 2302, "@tmz": 2303, "wing": 2304, "@fredzeppelin12": 2305, "disneyland": 2306, "duh": 2307, "prosecute": 2308, "@deptofdefense": 2309, "screw": 2310, "receives": 2311, "privilege": 2312, "extra": 2313, "escape": 2314, "unknown": 2315, "shock": 2316, "uses": 2317, "fail": 2318, "returning": 2319, "trait": 2320, "suck": 2321, "sucks": 2322, "hook": 2323, "cheap": 2324, "failed": 2325, "@keitholbermann": 2326, "biggest": 2327, "2nd": 2328, "bigger": 2329, "ignore": 2330, "british": 2331, "keeping": 2332, "men's": 2333, "relief": 2334, "math": 2335, "invite": 2336, "auto": 2337, "events": 2338, "@surfermom77": 2339, "intros": 2340, "committed": 2341, "risk": 2342, "punished": 2343, "wont": 2344, "wonderful": 2345, "stupidest": 2346, "#empirebvs": 2347, "insult": 2348, "meanwhile": 2349, "blow": 2350, "bitch": 2351, "tragic": 2352, "facebook": 2353, "z": 2354, "consequences": 2355, "@truthfeednews": 2356, "angry": 2357, "jeb": 2358, "prisoners": 2359, "costs": 2360, "allegations": 2361, "credibility": 2362, "secretly": 2363, "1c": 2364, "crew": 2365, "yo": 2366, "restrooms": 2367, "28": 2368, "@davidbrockdc": 2369, "priorities": 2370, "nigeria": 2371, "itself": 2372, "proves": 2373, "@borucjan": 2374, "@justinbieber": 2375, "48": 2376, "hour": 2377, "culture": 2378, "@statedept": 2379, "#imwithher": 2380, "owners": 2381, "rule": 2382, "mine": 2383, "minds": 2384, "climate": 2385, "@mattwalshblog": 2386, "value": 2387, "broke": 2388, "usually": 2389, "adorable": 2390, "biased": 2391, "@terrydemetriou": 2392, "israel": 2393, "announces": 2394, "hypocrites": 2395, "endorsement": 2396, "broken": 2397, "husband": 2398, "hundreds": 2399, "certain": 2400, "chuck": 2401, "hundred": 2402, "excited": 2403, "attending": 2404, "toilet": 2405, "@sammyrhodes": 2406, "extremist": 2407, "smoke": 2408, "tired": 2409, "nominee": 2410, "]": 2411, "sport": 2412, "nfl": 2413, "finger": 2414, "fingers": 2415, "tim": 2416, "flags": 2417, "@france24": 2418, "fda": 2419, "faster": 2420, "fantastic": 2421, "loose": 2422, "05": 2423, "spoke": 2424, "04": 2425, "@gwillowwilson": 2426, "@breezemufc": 2427, "saving": 2428, "pulled": 2429, "foundation": 2430, "stone": 2431, "ignorance": 2432, "spent": 2433, "acting": 2434, "ideas": 2435, "suggest": 2436, "suicide": 2437, "killings": 2438, "sooo": 2439, "hypocrite": 2440, "kills": 2441, "@davebeninger": 2442, "across": 2443, "kissing": 2444, "alert": 2445, "#nevertrump": 2446, "@statik310": 2447, "@benshapiro": 2448, "@talibkweli": 2449, "admin": 2450, "jay": 2451, "islands": 2452, "#9news": 2453, "x": 2454, "invasion": 2455, "mark": 2456, "minority": 2457, "interactions": 2458, "injured": 2459, "johnson": 2460, "jones": 2461, "india": 2462, "increased": 2463, "adolf": 2464, "jr": 2465, "purple": 2466, "nearly": 2467, "main": 2468, "stealing": 2469, "lawyer": 2470, "@nprnews": 2471, "laziness": 2472, "statements": 2473, "grown": 2474, "sodom": 2475, "accept": 2476, "scene": 2477, "goodness": 2478, "#kimdavis": 2479, "arm": 2480, "naked": 2481, "nasa": 2482, "#bernie2016": 2483, "thousands": 2484, "launch": 2485, "@dylanobrien": 2486, "sold": 2487, "apply": 2488, "within": 2489, "survive": 2490, "heterosexual": 2491, "accounts": 2492, "hes": 2493, "@tarekfatah": 2494, "@carolinagirl63": 2495, "host": 2496, "helped": 2497, "wise": 2498, "@doctorpetermd": 2499, "@carmencruz303": 2500, "moral": 2501, "2012": 2502, "tactic": 2503, "hardly": 2504, "#potus": 2505, "hatred": 2506, "@maydnusa": 2507, "skin": 2508, "russia": 2509, "clark": 2510, "doesnt": 2511, "turning": 2512, "reminds": 2513, "ohio": 2514, "clueless": 2515, "remove": 2516, "coffee": 2517, "dnc": 2518, "blm": 2519, "basically": 2520, "upon": 2521, "ship": 2522, "unreal": 2523, "offices": 2524, "passing": 2525, "@_floridaman": 2526, "barkley": 2527, "changing": 2528, "charleston": 2529, "vegetarian": 2530, "troops": 2531, "wars": 2532, "san": 2533, "checks": 2534, "boring": 2535, "sam": 2536, "drive": 2537, "drinking": 2538, "truck": 2539, "bar": 2540, "offensive": 2541, "barack": 2542, "rise": 2543, "olympics": 2544, "compare": 2545, "sigh": 2546, "despicable": 2547, "reporter": 2548, "related": 2549, "safer": 2550, "current": 2551, "sake": 2552, "believed": 2553, "danger": 2554, "udcaf": 2555, "demands": 2556, "@washtimes": 2557, "beginning": 2558, "orlando": 2559, "ugly": 2560, "behavior": 2561, "cowards": 2562, "couples": 2563, "unfortunately": 2564, "@kayburley": 2565, "dishonest": 2566, "disgusted": 2567, "partnership": 2568, "confused": 2569, "tweeting": 2570, "congratulations": 2571, "considered": 2572, "obamacare": 2573, "bastards": 2574, "conversation": 2575, "core": 2576, "correlation": 2577, "pandering": 2578, "devil": 2579, "@kazzaino": 2580, "@vj44": 2581, "por": 2582, "silly": 2583, "@johnpiper": 2584, "center": 2585, "bruce": 2586, "brazil": 2587, "causes": 2588, "nurses": 2589, "train": 2590, "rocket": 2591, "bowl": 2592, "shall": 2593, "brave": 2594, "brings": 2595, "businesses": 2596, "@wowsopunny": 2597, "cancer": 2598, "zika": 2599, "bye": 2600, "century": 2601, "@marcbrodyreal": 2602, "english": 2603, "nthat's": 2604, "planning": 2605, "trans": 2606, "@henderburn": 2607, "sharia": 2608, "breaks": 2609, "trip": 2610, "causing": 2611, "everyday": 2612, "trillion": 2613, "easier": 2614, "@thinkatheist": 2615, "pants": 2616, "93": 2617, "loser": 2618, "soros": 2619, "legs": 2620, "angel": 2621, "dc": 2622, "we'll": 2623, "play-doh": 2624, "homeland": 2625, "#equalpay": 2626, "@kellyoxford": 2627, "uh": 2628, "retweet": 2629, "@bamaperry": 2630, "conspiracy": 2631, "literally": 2632, "deadly": 2633, "quality": 2634, "dearborn": 2635, "decades": 2636, "bird": 2637, "listening": 2638, "@maxicat": 2639, "playstation": 2640, "@derpey": 2641, "progress": 2642, "4th": 2643, "believing": 2644, "bruh": 2645, "hole": 2646, "hostage-taker": 2647, "answers": 2648, "benefits": 2649, "prior": 2650, "yourselves": 2651, "creator": 2652, "stands": 2653, "pac": 2654, "actor": 2655, "supremacist": 2656, "quickly": 2657, "unemployment": 2658, "lighting": 2659, "hunt": 2660, "hispanic": 2661, "migrants": 2662, "bho": 2663, "@realstrongfacts": 2664, "logic": 2665, "sunday": 2666, "impossible": 2667, "cameron": 2668, "se": 2669, "@lightskinzayn": 2670, "pool": 2671, "christie": 2672, "steal": 2673, "values": 2674, "jerk": 2675, "she'll": 2676, "#berniesanders": 2677, "chose": 2678, "madness": 2679, "china's": 2680, "publicity": 2681, "bombs": 2682, "chick-fil-a": 2683, "proven": 2684, "borders": 2685, "knowledge": 2686, "rock": 2687, "steps": 2688, "2b": 2689, "@teenforbernie": 2690, "celebrity": 2691, "boss": 2692, "@peady63": 2693, "@rubyrose": 2694, "robbery": 2695, "#sydney": 2696, "adult": 2697, "worthy": 2698, "accountable": 2699, "circus": 2700, "cirillo": 2701, "#ottnews": 2702, "legally": 2703, "lebron": 2704, "calm": 2705, "rupert": 2706, "condolences": 2707, "purpose": 2708, "canada's": 2709, "wondering": 2710, "stat": 2711, "lay": 2712, "\u270c": 2713, "station": 2714, "videos": 2715, "protected": 2716, "stars": 2717, "process": 2718, "pathological": 2719, "blog": 2720, "career": 2721, "@stevestfler": 2722, "later": 2723, "closer": 2724, "mate": 2725, "@randomsillyshit": 2726, "\u2757": 2727, "lame": 2728, "roll": 2729, "strength": 2730, "2008": 2731, "#parisattacks": 2732, "laugh": 2733, "1e": 2734, "quotes": 2735, "@observer": 2736, "theory": 2737, "gangs": 2738, "udffd": 2739, "barry": 2740, "fyi": 2741, "@americanmex067": 2742, "named": 2743, "present": 2744, "drawn": 2745, "offended": 2746, "@forbes": 2747, "@israfel070": 2748, "threatens": 2749, "silent": 2750, "funds": 2751, "bank": 2752, "signed": 2753, "george": 2754, "disaster": 2755, "greenland": 2756, "teach": 2757, "arabia": 2758, "murders": 2759, "disease": 2760, "arrived": 2761, "goliath": 2762, "distraction": 2763, "divisive": 2764, "army": 2765, "window": 2766, "dna": 2767, "@erictrump": 2768, "gods": 2769, "obamas": 2770, "you'd": 2771, "pr": 2772, "farms": 2773, "england": 2774, "tomorrow": 2775, "nso": 2776, "fallen": 2777, "topic": 2778, "ends": 2779, "enraged": 2780, "entertainment": 2781, "@reuterslive": 2782, "european": 2783, "available": 2784, "relations": 2785, "whats": 2786, "@positronicwoman": 2787, "empty": 2788, "favor": 2789, "favorite": 2790, "nyt": 2791, "whitehouse": 2792, "@genemcvay": 2793, "finish": 2794, "tribute": 2795, "trial": 2796, "athlete": 2797, "ffs": 2798, "treat": 2799, "title": 2800, "western": 2801, "feelings": 2802, "trayvon": 2803, "regardless": 2804, "emergency": 2805, "ongoing": 2806, "direction": 2807, "@shelleyhennig": 2808, "handsome": 2809, "solution": 2810, "became": 2811, "destroying": 2812, "mostly": 2813, "gunfire": 2814, "posting": 2815, "taxpayers": 2816, "hearing": 2817, "sydney's": 2818, "becoming": 2819, "hates": 2820, "developing": 2821, "destruction": 2822, "design": 2823, "option": 2824, "wisdom": 2825, "somehow": 2826, "hated": 2827, "pretend": 2828, "random": 2829, "replace": 2830, "growing": 2831, "dinner": 2832, "mrs": 2833, "hannity": 2834, "type": 2835, "hello": 2836, "potential": 2837, "@gaetasusan": 2838, "field": 2839, "@davidgregory": 2840, "@maddowblog": 2841, "version": 2842, "benghazi": 2843, "language": 2844, "killers": 2845, "tacky": 2846, "rom\u00e2nia": 2847, "@gimpolice": 2848, "@ronsantofan": 2849, "@gideonresnick": 2850, "rolling": 2851, "elect": 2852, "veterans": 2853, "flip": 2854, "celebrities": 2855, "tries": 2856, "flight": 2857, "vets": 2858, "@redwoodgirl": 2859, "cc": 2860, "thug": 2861, "how's": 2862, "easily": 2863, "respond": 2864, "screwed": 2865, "belong": 2866, "economic": 2867, "effort": 2868, "@newscomauhq": 2869, "@davos": 2870, "attackers": 2871, "\u263a": 2872, "da": 2873, "view": 2874, "liars": 2875, "regular": 2876, "#maga": 2877, "walking": 2878, "@heytammybruce": 2879, "reliable": 2880, "facing": 2881, "brothers": 2882, "deductible": 2883, "towards": 2884, "liked": 2885, "aglow": 2886, "traditional": 2887, "00": 2888, "exposed": 2889, "sailors": 2890, "ran": 2891, "lived": 2892, "writing": 2893, "stance": 2894, "hospital": 2895, "@mashablenews": 2896, "udcb": 2897, "@jubals": 2898, "regret": 2899, "hateful": 2900, "empire": 2901, "#hoodsoff": 2902, "fb": 2903, "200": 2904, "ca": 2905, "@joyce_karam": 2906, "would've": 2907, "@marilocosta": 2908, "demand": 2909, "fans": 2910, "@businessinsider": 2911, "famous": 2912, "rescue": 2913, "les": 2914, "falling": 2915, "busy": 2916, "delusional": 2917, "dumber": 2918, "@kamvtv": 2919, "@cenkuygur": 2920, "institutional": 2921, "@kristenkallhovd": 2922, "complain": 2923, "blair": 2924, "integrity": 2925, "intelligent": 2926, "compared": 2927, "television": 2928, "interest": 2929, "gulf": 2930, "goat": 2931, "student": 2932, "biden": 2933, "could've": 2934, "invented": 2935, "science": 2936, "@erikaandiola": 2937, "giant": 2938, "german": 2939, "details": 2940, "union": 2941, "ireland": 2942, "watched": 2943, "@complexmusic": 2944, "groups": 2945, "illness": 2946, "@kgbveteran": 2947, "constitutional": 2948, "grief": 2949, "ignored": 2950, "immigration": 2951, "greatness": 2952, "considering": 2953, "push": 2954, "success": 2955, "discussion": 2956, "dewshine": 2957, "birth": 2958, "americas": 2959, "individuals": 2960, "tears": 2961, "tech": 2962, "disqualified": 2963, "@complexpop": 2964, "incident": 2965, "irrelevant": 2966, "clue": 2967, "court's": 2968, "#iran": 2969, "jordan": 2970, "josh": 2971, "journalists": 2972, "dress": 2973, "joy": 2974, "border": 2975, "frank": 2976, "@jjauthor": 2977, "fried": 2978, "jump": 2979, "1/2": 2980, "unemployed": 2981, "checked": 2982, "2.5": 2983, "keith": 2984, "dt": 2985, "assange": 2986, "charged": 2987, "talent": 2988, "drone": 2989, "ashamed": 2990, "articles": 2991, "@nswpolice": 2992, "allowing": 2993, "world's": 2994, "beyonc\u00e9": 2995, "closed": 2996, "covered": 2997, "gap": 2998, "cow": 2999, "taste": 3000, "it'll": 3001, "remind": 3002, "wild": 3003, "citizen": 3004, "#cnn": 3005, "james": 3006, "they'd": 3007, "target's": 3008, "alleged": 3009, "cpl": 3010, "bobby": 3011, "@fakesportscentr": 3012, "1000": 3013, "recent": 3014, "fave": 3015, "policewoman": 3016, "nif": 3017, "program": 3018, "pro": 3019, "personally": 3020, "shirt": 3021, "losers": 3022, "nyou": 3023, "si": 3024, "so-called": 3025, "[": 3026, "affordable": 3027, "sources": 3028, "predictions": 3029, "product": 3030, "phone": 3031, "@anonyops": 3032, "moved": 3033, "wwe": 3034, ":-(": 3035, "serving": 3036, "movement": 3037, "actress": 3038, "newton": 3039, "nuclear": 3040, "partner": 3041, "nno": 3042, "@bbctrending": 3043, "phony": 3044, "pharma": 3045, "@vitico46": 3046, "pakistan": 3047, "@appsame": 3048, "piss": 3049, "34": 3050, "pair": 3051, "sin": 3052, "#samuraijack": 3053, "profits": 3054, "loves": 3055, "@billpostmus": 3056, "address": 3057, "@waitwait": 3058, "@tomsteinfort": 3059, "players": 3060, ";-)": 3061, "27": 3062, "adults": 3063, "32": 3064, ":-)": 3065, "profit": 3066, "@ausnewsnetwork": 3067, "powers": 3068, "passengers": 3069, "piers": 3070, "lochte": 3071, "skills": 3072, "mexico": 3073, "mil": 3074, "solar": 3075, "park": 3076, "otherwise": 3077, "90": 3078, "slow": 3079, "@theroot": 3080, "showed": 3081, "shld": 3082, "smile": 3083, "pm": 3084, "`": 3085, "@adambaldwin": 3086, "paramedics": 3087, "yup": 3088, "senate": 3089, "programs": 3090, "smoking": 3091, "minorities": 3092, "admits": 3093, "#orlando": 3094, "motivated": 3095, "shine": 3096, "match": 3097, "njust": 3098, "#anonymous": 3099, "stream": 3100, "combined": 3101, "@zaynmalik": 3102, "invited": 3103, "strip": 3104, "strict": 3105, "celebration": 3106, "@draiochta14": 3107, "remain": 3108, "added": 3109, "blatant": 3110, "nurse": 3111, "solved": 3112, "ground": 3113, "praise": 3114, "bout": 3115, "comfort": 3116, "nut": 3117, "2a": 3118, "niagara": 3119, "@realronhoward": 3120, "irony": 3121, "prevent": 3122, "retailers": 3123, "searching": 3124, "julian": 3125, "1f": 3126, "decency": 3127, "rates": 3128, "@benaffleck": 3129, "shards": 3130, "carrier": 3131, "nigga": 3132, "polling": 3133, "positive": 3134, "@isletsoflngrhns": 3135, "search": 3136, "quiet": 3137, "sanctions": 3138, "victoria": 3139, "decided": 3140, "attended": 3141, "@nettaaa": 3142, "approval": 3143, "@antderosa": 3144, "tank": 3145, "deals": 3146, "judy": 3147, "@13spencer": 3148, "@gop": 3149, "com": 3150, "cold": 3151, "decisions": 3152, "allegedly": 3153, "udffe": 3154, "regarding": 3155, "practice": 3156, "mps": 3157, "journalist": 3158, "@earthbeauties": 3159, "senators": 3160, "coward": 3161, "fathers": 3162, "challenge": 3163, "@cmaconthehill": 3164, "expand": 3165, "@dailymailau": 3166, "entitled": 3167, "illegals": 3168, "holiday": 3169, "andy": 3170, "illuminati": 3171, "queen": 3172, "ily": 3173, "suckers": 3174, "messed": 3175, "benefit": 3176, "quasimodo": 3177, "340,000": 3178, "@wtffacts": 3179, "bachmann": 3180, "performed": 3181, "qbs": 3182, "classic": 3183, "extreme": 3184, "sit": 3185, "meh": 3186, "#pjnet": 3187, "ammunition": 3188, "road": 3189, "nra": 3190, "hug": 3191, "hr": 3192, "@australian": 3193, "shoes": 3194, "woah": 3195, "eventually": 3196, "prayer": 3197, "traffic": 3198, "19": 3199, "hurts": 3200, "162": 3201, "migrant": 3202, "minutes": 3203, "hypocritical": 3204, "hospitals": 3205, "percentage": 3206, "exact": 3207, "bombing": 3208, "@democratcespool": 3209, "equivalent": 3210, "#backtothefuture": 3211, "#hillaryclinton": 3212, "hypocrisy": 3213, "historic": 3214, "wet": 3215, "rob": 3216, "elsewhere": 3217, "bernie's": 3218, "xy": 3219, "eleven": 3220, "darkness": 3221, "@sassafrantz": 3222, "morality": 3223, "ad": 3224, "falls": 3225, "healthy": 3226, "closet": 3227, "interests": 3228, "bottom": 3229, "intolerance": 3230, "@cnnsitroom": 3231, "@donnabrazile": 3232, "sxsw": 3233, "symbol": 3234, "@zacksnyder": 3235, "effect": 3236, "sandy": 3237, "investigate": 3238, "dat": 3239, "amendment": 3240, "clip": 3241, "style": 3242, "crossed": 3243, "hiring": 3244, "incompetent": 3245, "cheat": 3246, "q": 3247, "daily": 3248, "classy": 3249, "rain": 3250, "encourage": 3251, "nominated": 3252, "150": 3253, "individual": 3254, "model": 3255, "raised": 3256, "click": 3257, "@djokernole": 3258, "@only4rm": 3259, "inhale": 3260, "injustice": 3261, "@thenewdeal": 3262, "prob": 3263, "factory": 3264, "insanity": 3265, "syrians": 3266, "alien": 3267, "@liztilley84": 3268, "display": 3269, "@galgadot": 3270, "confinement": 3271, "murderer": 3272, "@vine": 3273, "@anamikamadad": 3274, "leaves": 3275, "89": 3276, "orc": 3277, "legacy": 3278, "orange": 3279, "saved": 3280, "legged": 3281, "@richeisen": 3282, "deplorable": 3283, "connection": 3284, "@burgerking": 3285, "prepared": 3286, "scalia's": 3287, "@marylene58": 3288, "sides": 3289, "los": 3290, "abandoned": 3291, "funding": 3292, "leads": 3293, "gee": 3294, "las": 3295, "@krisjacob89": 3296, "basic": 3297, "orders": 3298, "afa": 3299, "represent": 3300, "laughable": 3301, "statistic": 3302, "fl": 3303, "@cameron_gray": 3304, "busted": 3305, "runs": 3306, "genuine": 3307, "season": 3308, "lowest": 3309, "settle": 3310, "concussions": 3311, "brainless": 3312, "stated": 3313, "smell": 3314, "sec": 3315, "burn": 3316, "prepare": 3317, "sc": 3318, "dept": 3319, "thru": 3320, "bigotry": 3321, "sr": 3322, "freak": 3323, "nbut": 3324, "9/11": 3325, "links": 3326, "@richardmadan": 3327, "founding": 3328, "lockdown": 3329, "controlled": 3330, "opportunity": 3331, "pregnant": 3332, "promise": 3333, "opinions": 3334, "located": 3335, "opens": 3336, "serves": 3337, "beast": 3338, "whose": 3339, "cop": 3340, "spot": 3341, "whom": 3342, "promote": 3343, "wednesday": 3344, "thx": 3345, "levels": 3346, "lgbt": 3347, "spoken": 3348, "bigot": 3349, "seconds": 3350, "fuckin": 3351, "corporate": 3352, "fruit": 3353, "thursday": 3354, "watchdog": 3355, "director": 3356, "license": 3357, "#ireland": 3358, "loool": 3359, "shown": 3360, "friday": 3361, "agrees": 3362, "difficult": 3363, "twist": 3364, "wounded": 3365, "batman": 3366, "followed": 3367, "turkey": 3368, "six": 3369, "comparison": 3370, "oregon": 3371, "9c": 3372, "#batman": 3373, "grand": 3374, "violent": 3375, "sexual": 3376, "competition": 3377, "organization": 3378, "key": 3379, "teaching": 3380, "figures": 3381, "poverty": 3382, "@alice_horan96": 3383, "complaining": 3384, "udce": 3385, "violates": 3386, "absurd": 3387, "ma": 3388, "@tobiascarrier": 3389, "domestic": 3390, "virgins": 3391, "spinning": 3392, "sexist": 3393, "bias": 3394, "stole": 3395, "#germanwings": 3396, "professional": 3397, "popular": 3398, "douche": 3399, "wrote": 3400, "compassion": 3401, "nhe": 3402, "murderers": 3403, "#demdebate": 3404, "places": 3405, "\u3002": 3406, "ate": 3407, "ni'm": 3408, "abt": 3409, "firearms": 3410, "delete": 3411, "plain": 3412, "@nikkisixx": 3413, "teams": 3414, "hmrc": 3415, "average": 3416, "@glinner": 3417, "comparing": 3418, "surgeon": 3419, "historically": 3420, "extremely": 3421, "missile": 3422, "rio": 3423, "homes": 3424, "ring": 3425, "selection": 3426, "screaming": 3427, "shits": 3428, "classified": 3429, "rising": 3430, "reverse": 3431, "340,001": 3432, "expression": 3433, "net": 3434, "fu": 3435, "gullible": 3436, "hollywood": 3437, "@ncgazette": 3438, "april": 3439, "yesss": 3440, "attempted": 3441, "attacked": 3442, "1.15": 3443, "@affanchowdhry": 3444, "prefer": 3445, "hobby": 3446, "firm": 3447, "@tgradous": 3448, "owe": 3449, "@mlighty60": 3450, "fiction": 3451, "hotel": 3452, "slowest": 3453, "@heatherfoxnews": 3454, "trade": 3455, "fell": 3456, "detroit": 3457, "achievement": 3458, "belongs": 3459, "@thepoke": 3460, "fetus": 3461, "sock": 3462, "port": 3463, "hq": 3464, "@girlsfortrump": 3465, "vanessa": 3466, "smith": 3467, "@davidsirota": 3468, "convince": 3469, "vape": 3470, "@eilperin": 3471, "bills": 3472, "content": 3473, "aware": 3474, "governors": 3475, "nazis": 3476, "homosexuality": 3477, "@ggreenwald": 3478, "races": 3479, "arent": 3480, "excuses": 3481, "file": 3482, "aw": 3483, "graham": 3484, "#hillary": 3485, "hoods": 3486, "1.5": 3487, "relationship": 3488, "penalty": 3489, "quran": 3490, "cia": 3491, "rcmp": 3492, "award": 3493, "awarded": 3494, "cry": 3495, "forcing": 3496, "colour": 3497, "homosexuals": 3498, "teens": 3499, "fuel": 3500, "#lindt": 3501, "bite": 3502, "#dumptrump": 3503, "@vivalaames": 3504, "nis": 3505, "@bobbyjindal": 3506, "coincidence": 3507, "genius": 3508, "access": 3509, "headed": 3510, "fat": 3511, "#whitehouse": 3512, "paul": 3513, "handing": 3514, "headlines": 3515, "flat": 3516, "myth": 3517, "range": 3518, "switch": 3519, "healthcare": 3520, "finished": 3521, "hampshire": 3522, "heading": 3523, "nit": 3524, "@dory": 3525, "nak": 3526, "@nme": 3527, "wilson": 3528, "hashtag": 3529, "reform": 3530, "newspaper": 3531, "patriots": 3532, "hat": 3533, "harder": 3534, "tactics": 3535, "tag": 3536, "savage": 3537, "@gcugini": 3538, "nit's": 3539, "fascist": 3540, "@question_arab": 3541, "98": 3542, "rape": 3543, "ties": 3544, "hating": 3545, "gesture": 3546, "fancy": 3547, "appear": 3548, "germans": 3549, "goals": 3550, "creature": 3551, "halal": 3552, "club": 3553, "saudis": 3554, "crook": 3555, "@slone": 3556, "underground": 3557, "nato": 3558, "financial": 3559, "payments": 3560, "crooks": 3561, "77": 3562, "mutations": 3563, "gomorrah": 3564, "bo": 3565, "yall": 3566, "slap": 3567, "ups": 3568, "taught": 3569, "rational": 3570, "fund": 3571, "automation": 3572, "fully": 3573, "hire": 3574, "@realdrgina": 3575, "mo": 3576, "#tedcruz": 3577, "participation": 3578, "moderate": 3579, "abroad": 3580, "rifles": 3581, "@nytimesphoto": 3582, "touch": 3583, "@griffwitte": 3584, "upset": 3585, "scam": 3586, "weapon": 3587, "app": 3588, "owning": 3589, "temporarily": 3590, "helps": 3591, "swear": 3592, "noh": 3593, "waters": 3594, "payers": 3595, "flooding": 3596, "confiscates": 3597, "#teenwolf": 3598, "birthday": 3599, "asshole": 3600, "144": 3601, "mutiny": 3602, "pretends": 3603, "snap": 3604, "commit": 3605, "tool": 3606, "all-star": 3607, "capital": 3608, "driving": 3609, "capture": 3610, "judges": 3611, "judgement": 3612, "pig": 3613, "2c": 3614, "victory": 3615, "worsen": 3616, "sergeant-at-arms": 3617, "bankers": 3618, "carne": 3619, "jimmy": 3620, "trojan": 3621, "decent": 3622, "@charmelodi": 3623, "dressed": 3624, "kate": 3625, "dream": 3626, "advance": 3627, "definition": 3628, "#p2": 3629, "malaysian": 3630, "36": 3631, "males": 3632, "stocks": 3633, "percent": 3634, "posted": 3635, "manager": 3636, "wanting": 3637, "defense": 3638, "offer": 3639, "saint": 3640, "drama": 3641, "candy": 3642, "doomed": 3643, "del": 3644, "marking": 3645, "storm": 3646, "@clarknt67": 3647, "#clinton": 3648, "speed": 3649, "celebrated": 3650, "trend": 3651, "edible": 3652, "edition": 3653, "investigations": 3654, "educated": 3655, "@trevso_electric": 3656, "outcome": 3657, "central": 3658, "woodhull": 3659, "speculation": 3660, "alternative": 3661, "@ststwo": 3662, "islamist": 3663, "photoshop": 3664, "shorter": 3665, "ouch": 3666, "casey": 3667, "simmons": 3668, "mars": 3669, "jackass": 3670, "ny": 3671, "strategist-turned-defector": 3672, "behaviour": 3673, "dealing": 3674, "@cinderella2b": 3675, "nwell": 3676, "massachusetts": 3677, "#nationalhugday": 3678, "massacre": 3679, "causation": 3680, "massive": 3681, "vetting": 3682, "students": 3683, "klan": 3684, "@cbcottawa": 3685, "disarm": 3686, "one's": 3687, "@teamcavuto": 3688, "built": 3689, "lesson": 3690, "leo": 3691, "bullet": 3692, "tweeted": 3693, "lots": 3694, "affect": 3695, "bully": 3696, "legend": 3697, "loud": 3698, "department": 3699, "aint": 3700, "stalks": 3701, "disappointed": 3702, "bathed": 3703, "4b": 3704, "africa": 3705, "lmaooo": 3706, "@thisisnafissa": 3707, "lock": 3708, "beats": 3709, "listened": 3710, "despite": 3711, "bunker": 3712, "@jessiejaneduff": 3713, "pocket": 3714, "plus": 3715, "onto": 3716, "walks": 3717, "@7newssydney": 3718, "weekend": 3719, "@brianmoore666": 3720, "logo": 3721, "knife": 3722, "omfg": 3723, "bastard": 3724, "@mtvteenwolf": 3725, "lands": 3726, "often": 3727, "bypass": 3728, "demanding": 3729, "@jaredwyand": 3730, "@rolandsmartin": 3731, "cake": 3732, "kudos": 3733, "kouachi": 3734, "mafia": 3735, "knowing": 3736, "mail": 3737, "bars": 3738, "camera": 3739, "turns": 3740, "largest": 3741, "protecting": 3742, "akira": 3743, "26": 3744, "prosecuted": 3745, "learning": 3746, "removed": 3747, "disqualify": 3748, "le": 3749, "lowered": 3750, "@bklynmiddleton": 3751, "#ottawashooting": 3752, "sight": 3753, "lawmakers": 3754, "divide": 3755, "basis": 3756, "@canoe": 3757, "@meetthepress": 3758, "butterfly": 3759, "denmark": 3760, "outrageous": 3761, "unite": 3762, "translucent": 3763, "transgenders": 3764, "hurting": 3765, "sea": 3766, "cheering": 3767, "traumatic": 3768, "sharp": 3769, "resign": 3770, "era": 3771, "shopped": 3772, "episode": 3773, "dam": 3774, "indian": 3775, "successful": 3776, "backs": 3777, "@housecracka": 3778, "outstanding": 3779, "awkward": 3780, "unavailable": 3781, "member": 3782, "anne": 3783, "inquiry": 3784, "erupts": 3785, "nthey": 3786, "@stellaaa": 3787, "idiotic": 3788, "danes": 3789, "suit": 3790, "es": 3791, "emma": 3792, "seek": 3793, "dang": 3794, "idk": 3795, "idol": 3796, "@thenewblack138": 3797, "persons": 3798, "resigns": 3799, "reservist": 3800, "error": 3801, "include": 3802, "spain": 3803, "nshe": 3804, "#cbcott": 3805, "bother": 3806, "@coiiegecampuses": 3807, "@rudygiulianigop": 3808, "incorrect": 3809, "whaaat": 3810, "erdogan": 3811, "petty": 3812, "min": 3813, "nuke": 3814, "currently": 3815, "vegan": 3816, "puppet": 3817, "mi": 3818, "nov": 3819, "traitor": 3820, "uncle": 3821, "ignoring": 3822, "incredibly": 3823, "vegas": 3824, "amari": 3825, "@coinabs": 3826, "@julienpain": 3827, "elite": 3828, "southwest": 3829, "wondered": 3830, "angers": 3831, "channel": 3832, "@davehydesports": 3833, "treason": 3834, "@dailymailceleb": 3835, "immigrant": 3836, "entering": 3837, "souls": 3838, "custody": 3839, "cuts": 3840, "petition": 3841, "ice": 3842, "awww": 3843, "bacon": 3844, "unacceptable": 3845, "@thei100": 3846, "neutral": 3847, "@jcschmieder": 3848, "@highkeychildish": 3849, "96": 3850, "equally": 3851, "treatment": 3852, "\u043d\u0435": 3853, "#rio2016": 3854, "entrance": 3855, "til": 3856, "environment": 3857, "web": 3858, "dementia": 3859, "demo": 3860, "ol": 3861, "cruel": 3862, "tpp": 3863, "@sleepinthegardn": 3864, "referring": 3865, "divided": 3866, "fixed": 3867, "exit": 3868, "tie": 3869, "preach": 3870, "denver": 3871, "disrespect": 3872, "cos": 3873, "fleas": 3874, "disqualifies": 3875, "normally": 3876, "@justconservativ": 3877, "exchange": 3878, "copyright": 3879, "neighborhood": 3880, "note": 3881, "diet": 3882, "repeatedly": 3883, "abe": 3884, "respected": 3885, "opposed": 3886, "tx": 3887, "ty": 3888, "parade": 3889, "ooh": 3890, "ford": 3891, "fooled": 3892, "throwing": 3893, "parallel": 3894, "oppose": 3895, "recently": 3896, "dickie": 3897, "replaced": 3898, "cultural": 3899, "forgive": 3900, "@france24_en": 3901, "@natgeo": 3902, "situations": 3903, "bear": 3904, "threw": 3905, "devices": 3906, "oooh": 3907, "repeated": 3908, "ctv": 3909, "trading": 3910, "\u2606": 3911, "#hillary2016": 3912, "depends": 3913, "beloved": 3914, "correctly": 3915, "currency": 3916, "pork": 3917, "pour": 3918, "unisex": 3919, "deport": 3920, "discuss": 3921, "discrimination": 3922, "awards": 3923, "discriminate": 3924, "discovered": 3925, "@msleamichele": 3926, "resources": 3927, "wedding": 3928, "asses": 3929, "overseas": 3930, "optics": 3931, "opposite": 3932, "@keithkote": 3933, "nowhere": 3934, "thugs": 3935, "desire": 3936, "esp": 3937, "desperately": 3938, "everyone's": 3939, "er": 3940, "owner": 3941, "nsee": 3942, "saturday": 3943, ":p": 3944, "#sanbernardino": 3945, "shoppers": 3946, "nwhy": 3947, "required": 3948, "shocker": 3949, "crashed": 3950, "slavery": 3951, "nin": 3952, "travel": 3953, "udfff": 3954, "nightmare": 3955, "critical": 3956, "understanding": 3957, "triple": 3958, "decade": 3959, "crack": 3960, "nudies": 3961, "@goldietaylor": 3962, "dunk": 3963, "embarrassment": 3964, "featured": 3965, "authority": 3966, "wealth": 3967, "obnoxious": 3968, "@women4bernie": 3969, "troll": 3970, "obstruction": 3971, "debunked": 3972, "retail": 3973, "@govmikehuckabee": 3974, "failure": 3975, "sane": 3976, "beings": 3977, "#wtf": 3978, "bae": 3979, "audit": 3980, "fame": 3981, "daughter's": 3982, "york": 3983, "effects": 3984, "tonight's": 3985, "austin": 3986, "editor": 3987, "badly": 3988, "elephant": 3989, "david": 3990, "torture": 3991, "nixon": 3992, "bail": 3993, "06": 3994, "underway": 3995, "nwe": 3996, "audience": 3997, "farewell": 3998, "@12livelarge": 3999, "youtube": 4000, "dealership": 4001, "tommy": 4002, "@joyannreid": 4003, "understood": 4004, "03": 4005, "counting": 4006, "feds": 4007, "religions": 4008, "sale": 4009, "nthat": 4010, "filled": 4011, "degree": 4012, "film": 4013, "tryin": 4014, "represents": 4015, "donating": 4016, "final": 4017, "pain": 4018, "@sensanders": 4019, "fam": 4020, "officers": 4021, "dorothy": 4022, "santa": 4023, "explanation": 4024, "deliberately": 4025, "ng": 4026, "base": 4027, "whattt": 4028, "weasel": 4029, "unfortunate": 4030, "@alfredspellman": 4031, "believers": 4032, "crowd": 4033, "org": 4034, "beer": 4035, "\u25ba": 4036, "athletes": 4037, "@wasalwaysee": 4038, "figured": 4039, "trusted": 4040, "employed": 4041, "bankruptcy": 4042, "employee": 4043, "dropping": 4044, "refused": 4045, "nomination": 4046, "^": 4047, "declare": 4048, "encouraged": 4049, "banning": 4050, "odd": 4051, "fellow": 4052, "@johnkerry": 4053, "signs": 4054, "@jrothenbergtv": 4055, "wheres": 4056, "offend": 4057, "feminist": 4058, "feminists": 4059, "unfair": 4060, "deductibles": 4061, "regularly": 4062, "dragging": 4063, "begins": 4064, "@richarddawkins": 4065, "@1capplegate": 4066, "tip": 4067, "originals": 4068, "trudeau": 4069, "repubs": 4070, "cue": 4071, "tea": 4072, "anger": 4073, "@steph93065": 4074, "warning": 4075, "vehicle": 4076, "47": 4077, "charges": 4078, "charging": 4079, "indonesian": 4080, "indictment": 4081, "@countermoonbat": 4082, "breeds": 4083, "puts": 4084, "amid": 4085, "character": 4086, "incompetence": 4087, "@lolgop": 4088, "shark": 4089, "persian": 4090, "perjury": 4091, "@lnventlons": 4092, "cheney": 4093, "boom": 4094, "books": 4095, "qualified": 4096, "@redrising11": 4097, "@bambookiller": 4098, "illegally": 4099, "@creepingsharia": 4100, "@daddylouist": 4101, "womens": 4102, "spare": 4103, "allows": 4104, "strike": 4105, "zones": 4106, "alot": 4107, "1991": 4108, "@ottawasuncom": 4109, "celebreties": 4110, "stronger": 4111, "philosophy": 4112, "cell": 4113, "mayor": 4114, "warner": 4115, "verification": 4116, "65": 4117, "@bbcscotlandnews": 4118, "mcdonalds": 4119, "vet": 4120, "international": 4121, "champion": 4122, "intelligence": 4123, "specific": 4124, "insulting": 4125, "2e": 4126, "ambulance": 4127, "sector": 4128, "\u0443": 4129, "intolerant": 4130, "@daily_politics": 4131, "merica": 4132, "merit": 4133, "bogus": 4134, "superman": 4135, "70": 4136, "print": 4137, "shed": 4138, "sheep": 4139, "quoted": 4140, "hostage-taking": 4141, "mirrors": 4142, "hospitalized": 4143, "chump": 4144, "churches": 4145, "@audraequalitymc": 4146, "@debra0827": 4147, "@lilagracerose": 4148, "@uber": 4149, "17": 4150, "#popefrancis": 4151, "honorable": 4152, "racing": 4153, "wasn": 4154, "homophobic": 4155, "cities": 4156, "citing": 4157, "boats": 4158, "holocaust": 4159, "misguided": 4160, "minus": 4161, "wives": 4162, "minor": 4163, "suffer": 4164, "suffering": 4165, "mexican": 4166, "@redsteeze": 4167, "identify": 4168, "chill": 4169, "icon": 4170, "suggesting": 4171, "ann": 4172, "suing": 4173, "@danscavino": 4174, "xx": 4175, "sooner": 4176, "chocolat": 4177, "hunting": 4178, "mike": 4179, "sum": 4180, "chocolate": 4181, "priority": 4182, "sons": 4183, "humor": 4184, "scum": 4185, "quick": 4186, "she'd": 4187, "hugs": 4188, "@avitalleibovich": 4189, "bollocks": 4190, "material": 4191, "@luqman255": 4192, "49": 4193, "italy": 4194, "buildings": 4195, "aim": 4196, "@bryanboy": 4197, "rude": 4198, "lesbian": 4199, "propose": 4200, "bullets": 4201, "rubio": 4202, "@buzzfeedoz": 4203, "legit": 4204, "legalize": 4205, "leg": 4206, "setting": 4207, "led": 4208, "starving": 4209, "@martinbureau1": 4210, "@callum_sr": 4211, "lawsuits": 4212, "500,000": 4213, "laura": 4214, "setup": 4215, "luckily": 4216, "latter": 4217, "lately": 4218, "@tcmccarthy_": 4219, "button": 4220, "affairs": 4221, "properly": 4222, "@massdeception1": 4223, "budget": 4224, "breed": 4225, "lo": 4226, "bribery": 4227, "secretary": 4228, "project": 4229, "spy": 4230, "@bms_thadcastle": 4231, "promised": 4232, "promises": 4233, "breakdown": 4234, "aged": 4235, "agency": 4236, "pointing": 4237, "locked": 4238, "logical": 4239, "#trumptrain": 4240, "likes": 4241, "bread": 4242, "lone": 4243, "stabbing": 4244, "ah": 4245, "@brianboru7479": 4246, "brown": 4247, "lier": 4248, "pls": 4249, "pleased": 4250, "liberty": 4251, "rounds": 4252, "vacation": 4253, "landmarks": 4254, "c'est": 4255, "pink": 4256, "jury": 4257, "capable": 4258, "pigs": 4259, "jumped": 4260, "captured": 4261, "march": 4262, "jokes": 4263, "margin": 4264, "marine": 4265, "caring": 4266, "warned": 4267, "psycho": 4268, "#syria": 4269, "puke": 4270, "role": 4271, "roger": 4272, "japan": 4273, "pull": 4274, "bowie": 4275, "jake": 4276, "speedo": 4277, "j": 4278, "ive": 4279, "@beck": 4280, "6.9": 4281, "@susansarandon": 4282, "warming": 4283, "katy": 4284, "ked": 4285, "advice": 4286, "lynch": 4287, "visa": 4288, "stayed": 4289, "kuantan": 4290, "planking": 4291, "@marcorubio": 4292, "knock": 4293, "cameras": 4294, "alcohol": 4295, "mainstream": 4296, "rooms": 4297, "kingdom": 4298, "kinds": 4299, "spinach": 4300, "stickers": 4301, "campaigning": 4302, "camps": 4303, "@ceydak": 4304, "stolen": 4305, "#nhl": 4306, "manifesto": 4307, "proving": 4308, "kenya": 4309, "kenny": 4310, "kennedy": 4311, "viewers": 4312, "seven": 4313, "boat": 4314, "beard": 4315, "@kurtschlichter": 4316, "motive": 4317, "@drottm": 4318, "theres": 4319, "nasty": 4320, "block": 4321, "mix": 4322, "appreciate": 4323, "gang": 4324, "#dylannroof": 4325, "tests": 4326, "wat": 4327, "tanker": 4328, "graphic": 4329, "giuliani": 4330, "commitment": 4331, "arrive": 4332, "hang": 4333, "popularity": 4334, "blocked": 4335, "terms": 4336, "thin": 4337, "shite": 4338, "accepted": 4339, "sayin": 4340, "raped": 4341, "harry": 4342, "#lgbt": 4343, "review": 4344, "unlike": 4345, "@specialkmb1969": 4346, "artist": 4347, "#4u9525": 4348, "complicit": 4349, "applies": 4350, "cohen": 4351, "coast": 4352, "accidents": 4353, "texas": 4354, "mountain": 4355, "th": 4356, "bites": 4357, "comfortable": 4358, "conclusion": 4359, "that'll": 4360, "te": 4361, "rats": 4362, "@pjstrikeforce": 4363, "concert": 4364, "reach": 4365, "germanwings": 4366, "pressure": 4367, "richer": 4368, "geoblock": 4369, "101": 4370, "7th": 4371, "tbh": 4372, "con": 4373, "@anonyaussie": 4374, "confession": 4375, "confess": 4376, "hahahaha": 4377, "murderous": 4378, "path": 4379, "hadn't": 4380, "hadley": 4381, "graves": 4382, "@latikambourke": 4383, "blessing": 4384, "blames": 4385, "computers": 4386, "approved": 4387, "tasteless": 4388, "@us_army_vet": 4389, "naive": 4390, "arrogant": 4391, "previous": 4392, "complex": 4393, "gorgeous": 4394, "hiked": 4395, "hijacked": 4396, "@un": 4397, "thou": 4398, "containing": 4399, "contain": 4400, "raises": 4401, "@sr0bi": 4402, "teen": 4403, "hers": 4404, "@andrewzimmern": 4405, "@dlcama": 4406, "@firstwefeast": 4407, "parker": 4408, "freaky": 4409, "wide": 4410, "@ash_bell__": 4411, "surrounded": 4412, "@lesleyclark": 4413, "university": 4414, "universal": 4415, "abort": 4416, "holder": 4417, "goin": 4418, "fought": 4419, "controversial": 4420, "utter": 4421, "hitting": 4422, "hits": 4423, "ten": 4424, "surgery": 4425, "#equality": 4426, "contractor": 4427, "historical": 4428, "accused": 4429, "tend": 4430, "76": 4431, "rigged": 4432, "unlawful": 4433, "snopes": 4434, "morals": 4435, "swiss": 4436, "reaction": 4437, "@arendabdoory": 4438, "governments": 4439, "winter": 4440, "hearts": 4441, "clothing": 4442, "shitty": 4443, "gov't": 4444, "grace": 4445, "passport": 4446, "nazi": 4447, "heck": 4448, "#lockherup": 4449, "appalling": 4450, "reasonable": 4451, "areas": 4452, "gosh": 4453, "muscle": 4454, "@santiagos58": 4455, "wishes": 4456, "closes": 4457, "swim": 4458, "#climatechange": 4459, "@magnifier661": 4460, "retired": 4461, "cap": 4462, "cancel": 4463, "declaring": 4464, "cancelled": 4465, "define": 4466, "#fitness": 4467, "root": 4468, "deer": 4469, "vigoda": 4470, "sh": 4471, "orphans": 4472, "sexually": 4473, "pas": 4474, "unnecessary": 4475, "58": 4476, "composite": 4477, "blah": 4478, "defined": 4479, "retirement": 4480, "beg": 4481, "@krispysmore": 4482, "85": 4483, "vile": 4484, "country_codes": 4485, "parts": 4486, "udfb": 4487, "@sdavld": 4488, "delusion": 4489, "waited": 4490, "@vanessahudgens": 4491, "yuk": 4492, "wales": 4493, "yours": 4494, "description": 4495, "beauty": 4496, "buddy": 4497, "deserved": 4498, "@mealsaps": 4499, "sets": 4500, "#wheredidthepollgo": 4501, "salary": 4502, "corner": 4503, "para": 4504, "bin": 4505, "#america": 4506, "parent": 4507, "#toronto": 4508, "beating": 4509, "opportunities": 4510, "poison": 4511, "controls": 4512, "bigoted": 4513, "walls": 4514, "britain": 4515, "@kfaulders": 4516, "billions": 4517, "pockets": 4518, "cont": 4519, "brotherhood": 4520, "@kevinirishndhas": 4521, "rotten": 4522, "corp": 4523, "conscience": 4524, "@kaylabradstreet": 4525, "plant": 4526, "rhetoric": 4527, "plate": 4528, "vision": 4529, "conclusions": 4530, "visited": 4531, "@pudingtane": 4532, "97": 4533, "rover": 4534, "representations": 4535, "corrupted": 4536, "platform": 4537, "#flint": 4538, "@wearetmz": 4539, "rezaian": 4540, "conference": 4541, "congressional": 4542, "correction": 4543, "#endviolence": 4544, "brains": 4545, "}": 4546, "burgers": 4547, "depression": 4548, "burka": 4549, "burning": 4550, "confirmation": 4551, "rewarded": 4552, "player": 4553, "@westxgal": 4554, "@21stcenttemplar": 4555, "burned": 4556, "walton": 4557, "courts": 4558, "capitalist": 4559, "beside": 4560, "@seasyne": 4561, "customer": 4562, "useful": 4563, "curtain": 4564, "curry": 4565, "@mooniightmags": 4566, "washed": 4567, "boo": 4568, "paranoid": 4569, ":[": 4570, "@michellefields": 4571, "rides": 4572, "shaun": 4573, "cmon": 4574, "coat": 4575, "performance": 4576, "code": 4577, "#donaldtrump": 4578, "warriors": 4579, "chasing": 4580, "believable": 4581, "crash": 4582, "crass": 4583, "residents": 4584, "dads": 4585, "separation": 4586, "daddy": 4587, "cheater": 4588, "zuckerberg": 4589, "besides": 4590, "@jstines3paints": 4591, "#vincennes": 4592, "@lmdiet67": 4593, "400,000": 4594, "personality": 4595, "sacha": 4596, "400": 4597, "chinese": 4598, "shoe": 4599, "@lesliemarshall": 4600, "below": 4601, "@ucantbesrs": 4602, "@lifeasrednecks": 4603, "pen": 4604, "citation": 4605, "penis": 4606, "belt": 4607, "crusaders": 4608, "@umterps": 4609, "@walmart": 4610, "claiming": 4611, "crowded": 4612, "sheesh": 4613, "responses": 4614, "valerie": 4615, "resident": 4616, "cleveland": 4617, "criticize": 4618, "shooters": 4619, "cupboard": 4620, "@un_women": 4621, "blowing": 4622, "various": 4623, "bell": 4624, "@ryanlochte": 4625, "penny": 4626, "7a": 4627, "useless": 4628, ":{": 4629, "ownership": 4630, "russians": 4631, "cubs": 4632, "shes": 4633, "wasnt": 4634, "payer": 4635, "declaration": 4636, "una": 4637, "dance": 4638, "rocks": 4639, "debates": 4640, "como": 4641, "communist": 4642, "unfolding": 4643, "unto": 4644, "@lyndag1963": 4645, "9news": 4646, "committing": 4647, "requires": 4648, "cater": 4649, "retire": 4650, "vetted": 4651, "ours": 4652, "ourselves": 4653, "@mkues65": 4654, "reputation": 4655, "cat": 4656, "rocky": 4657, "should've": 4658, "boxing": 4659, "biafrans": 4660, "#sad": 4661, "decides": 4662, "box": 4663, "pieces": 4664, "cavs": 4665, "compassionate": 4666, "shortly": 4667, "deceptive": 4668, "deception": 4669, "5th": 4670, "picked": 4671, "#uniteblue": 4672, "6-1": 4673, "@randpaul": 4674, "#sagawards": 4675, "cbd": 4676, "richards": 4677, "darwin": 4678, "colored": 4679, "verified": 4680, "darn": 4681, "pets": 4682, "colonel": 4683, "collision": 4684, "versus": 4685, "cp": 4686, "peter": 4687, "chapter": 4688, "researchers": 4689, "@larsloving": 4690, "cpr": 4691, "pack": 4692, "@rubenbolling": 4693, "chaos": 4694, "pervert": 4695, "passports": 4696, "positions": 4697, "cbs": 4698, "unusual": 4699, "umm": 4700, "#clintoncash": 4701, "@travelleisure": 4702, "blast": 4703, "#scotusgaymarriage": 4704, "rescued": 4705, "blatt": 4706, "dave": 4707, "cells": 4708, "@scapesrus": 4709, "cents": 4710, "column": 4711, "outraged": 4712, "phelps": 4713, "covering": 4714, "convinced": 4715, "lobby": 4716, "shove": 4717, "@arstechnica": 4718, "something's": 4719, "modern": 4720, "anyways": 4721, "highest": 4722, "scientists": 4723, "survey": 4724, "monday": 4725, "surprises": 4726, "rage": 4727, "hitler's": 4728, "radio": 4729, "\u203c": 4730, "hockey": 4731, "mixture": 4732, "mixed": 4733, "hired": 4734, "@arron_crascall": 4735, "someone's": 4736, "monger": 4737, "talented": 4738, "solo": 4739, "taker": 4740, "solve": 4741, "mosque": 4742, "@sport_simon": 4743, "winners": 4744, "130m": 4745, "switzerland": 4746, "switched": 4747, "morally": 4748, "swing": 4749, "wiped": 4750, "@arianagrande": 4751, "@doctort1992": 4752, "montrouge": 4753, "swimming": 4754, "mission": 4755, "holes": 4756, "hollande": 4757, "withheld": 4758, "@davidkli": 4759, "sundays": 4760, "hum": 4761, "songs": 4762, "announced": 4763, "hurry": 4764, "hv": 4765, "prisoner": 4766, "iceberg": 4767, "icymi": 4768, "id": 4769, "identified": 4770, "active": 4771, "questionable": 4772, "merry": 4773, "sudden": 4774, "activity": 4775, "#medicine": 4776, "mothers": 4777, "supplies": 4778, "supply": 4779, "scotland": 4780, "seemed": 4781, "homicide": 4782, "homosexual": 4783, "achieve": 4784, "@staronline": 4785, "honored": 4786, "hood": 4787, "achieved": 4788, "hopes": 4789, "@defendingtheusa": 4790, "#martinpl": 4791, "#martinplace": 4792, "@deborahlovesusa": 4793, "misery": 4794, "mirror": 4795, "witness": 4796, "hound": 4797, "imo": 4798, "@speakerryan": 4799, "hall": 4800, "geez": 4801, "theme": 4802, "@evansposts": 4803, "gene": 4804, "\u0441\u0448\u0430": 4805, "geneva": 4806, "geo": 4807, "gdp": 4808, "theirs": 4809, "tf": 4810, "@andreapetkovic": 4811, "nailed": 4812, "text": 4813, "girlfriend": 4814, "testing": 4815, "scare": 4816, "tha": 4817, "@ewerickson": 4818, "absence": 4819, "art": 4820, "naval": 4821, "wikileaks": 4822, "@feministdan": 4823, "fry": 4824, "thier": 4825, "\u2192": 4826, "fucks": 4827, "theyre": 4828, "furries": 4829, "@fallontonight": 4830, "native": 4831, "natgeo": 4832, "nat": 4833, "therefore": 4834, "@plantflowes": 4835, "narcissistic": 4836, "@amymek": 4837, "scaring": 4838, "11,000": 4839, "snow": 4840, "glory": 4841, "pressed": 4842, "11k": 4843, "multiple": 4844, "groth": 4845, "soft": 4846, "@the_ryan_kelley": 4847, "mr.president": 4848, "ray": 4849, "guilt": 4850, "pretending": 4851, "movies": 4852, "@anonymouspress": 4853, "taxpayer": 4854, "hack": 4855, "hacking": 4856, "hahahah": 4857, "@soul_be_it": 4858, "reached": 4859, "@drscott_atlanta": 4860, "arab": 4861, "greater": 4862, "mystery": 4863, "arming": 4864, "reads": 4865, "@thearsenalrdu": 4866, "teeth": 4867, "@sonofliberty357": 4868, "@theanonmessage": 4869, "#kkk": 4870, "developed": 4871, "300": 4872, "gotten": 4873, "argue": 4874, "murray": 4875, "sociopath": 4876, "graph": 4877, "grasping": 4878, "grateful": 4879, "react": 4880, "friendly": 4881, "impeach": 4882, "implying": 4883, "steph": 4884, "knives": 4885, "magic": 4886, "madison": 4887, "steak": 4888, "stays": 4889, "2006": 4890, "@cbcpolitics": 4891, "label": 4892, "spirit": 4893, "larry": 4894, "af": 4895, "lunatic": 4896, "2013": 4897, "laugh-in": 4898, "profiling": 4899, "#sxsw": 4900, "@cbcsaltzman": 4901, "stepped": 4902, "@biasedgirl": 4903, "stood": 4904, "justify": 4905, "justin": 4906, "karma": 4907, "aliens": 4908, "worship": 4909, "stones": 4910, "manipulation": 4911, "@channeltennews": 4912, "manipulating": 4913, "spending": 4914, "@change": 4915, "#nigeria": 4916, "@bestlemming": 4917, "man's": 4918, "2000": 4919, "alexander": 4920, "ak": 4921, "lsu": 4922, "lawsuit": 4923, "affair": 4924, "licence": 4925, "stale": 4926, "promoting": 4927, "staged": 4928, "lifted": 4929, "sponsor": 4930, "spontaneous": 4931, "stab": 4932, "progressive": 4933, "lil": 4934, "agents": 4935, "wrath": 4936, "linked": 4937, "listed": 4938, "#opchaos": 4939, "lmaoo": 4940, "progressives": 4941, "libya": 4942, "junk": 4943, "21st": 4944, "ahhh": 4945, "seaworld": 4946, "state's": 4947, "2017": 4948, "@tdortchlee": 4949, "aircraft": 4950, "\u0639\u0644\u0649": 4951, "spit": 4952, "@c5hardtop1999": 4953, "#nra": 4954, "legislation": 4955, "lego": 4956, "leonardo": 4957, "@bsbfankaren": 4958, "loretta": 4959, "lords": 4960, "property": 4961, "@blancobandiito": 4962, "library": 4963, "implies": 4964, "june": 4965, "july": 4966, "insight": 4967, "med": 4968, "spanish": 4969, "inspired": 4970, "#moron": 4971, "meaningless": 4972, "\u061f": 4973, "insider": 4974, "xd": 4975, "meal": 4976, "specifically": 4977, "stunt": 4978, "interrogation": 4979, "@bbcsport": 4980, "stubborn": 4981, "worker": 4982, "intent": 4983, "su": 4984, "inmate": 4985, "pro-life": 4986, "@terrapinhoops": 4987, "actors": 4988, "impressed": 4989, "impressive": 4990, "improve": 4991, "inappropriate": 4992, "included": 4993, "includes": 4994, "income": 4995, "increases": 4996, "@omegaman58": 4997, "indians": 4998, "indoctrination": 4999}